{"OnlineId":6787,"OnlineStatus":"RANKED","LegacyId":"julientheroo_-_keygen_church_-_tenebre_rosso_sangue","SongName":"Keygen Church - Tenebre Rosso Sangue","Mappers":["JulienTheRoo"],"Title":"Keygen Church - Tenebre Rosso Sangue","Duration":230211,"Difficulty":5,"CustomDifficultyName":"P-2","StarRating":6.9045115,"Notes":[{"Time":341,"X":0,"Y":2},{"Time":511,"X":0,"Y":0},{"Time":682,"X":1,"Y":2},{"Time":1023,"X":1,"Y":0},{"Time":1364,"X":2,"Y":2},{"Time":1705,"X":0,"Y":1},{"Time":2046,"X":2,"Y":1},{"Time":2386,"X":0,"Y":2},{"Time":2727,"X":2,"Y":0},{"Time":2898,"X":1,"Y":2},{"Time":3068,"X":1,"Y":0},{"Time":3409,"X":0,"Y":2},{"Time":3750,"X":0,"Y":0},{"Time":4091,"X":1,"Y":2},{"Time":4432,"X":2,"Y":0},{"Time":4773,"X":0,"Y":1},{"Time":5114,"X":2,"Y":1},{"Time":5455,"X":0,"Y":2},{"Time":5625,"X":2,"Y":2},{"Time":5796,"X":1,"Y":0},{"Time":6136,"X":1,"Y":2},{"Time":6477,"X":0,"Y":0},{"Time":6818,"X":0,"Y":2},{"Time":7159,"X":2,"Y":0},{"Time":7500,"X":0,"Y":1},{"Time":7841,"X":2,"Y":1},{"Time":8182,"X":0,"Y":2},{"Time":8352,"X":1,"Y":0},{"Time":8523,"X":1,"Y":2},{"Time":8864,"X":2,"Y":0},{"Time":9205,"X":2,"Y":2},{"Time":9546,"X":1,"Y":0},{"Time":9886,"X":0,"Y":2},{"Time":10227,"X":2,"Y":1},{"Time":10568,"X":0,"Y":1},{"Time":10909,"X":2,"Y":0},{"Time":11080,"X":1,"Y":2},{"Time":11250,"X":1,"Y":0},{"Time":11421,"X":1,"Y":2},{"Time":11591,"X":1,"Y":0},{"Time":11761,"X":2,"Y":2},{"Time":11932,"X":0,"Y":0},{"Time":12102,"X":2,"Y":1},{"Time":12273,"X":0,"Y":1},{"Time":12443,"X":2,"Y":2},{"Time":12614,"X":0,"Y":2},{"Time":12784,"X":2,"Y":1},{"Time":12955,"X":0,"Y":0},{"Time":13125,"X":1,"Y":2},{"Time":13296,"X":2,"Y":0},{"Time":13466,"X":2,"Y":2},{"Time":13636,"X":0,"Y":1},{"Time":13807,"X":1,"Y":1},{"Time":13977,"X":2,"Y":0},{"Time":14148,"X":1,"Y":2},{"Time":14318,"X":1,"Y":0},{"Time":14489,"X":2,"Y":2},{"Time":14659,"X":0,"Y":0},{"Time":14830,"X":1,"Y":2},{"Time":15000,"X":1,"Y":0},{"Time":15171,"X":2,"Y":2},{"Time":15341,"X":2,"Y":0},{"Time":15511,"X":1,"Y":2},{"Time":15682,"X":0,"Y":0},{"Time":15852,"X":2,"Y":1},{"Time":16023,"X":0,"Y":2},{"Time":16193,"X":1,"Y":0},{"Time":16364,"X":1,"Y":2},{"Time":16534,"X":1,"Y":1},{"Time":16705,"X":2,"Y":0},{"Time":16875,"X":0,"Y":1},{"Time":17046,"X":2,"Y":1},{"Time":17216,"X":0,"Y":2},{"Time":17386,"X":2,"Y":1},{"Time":17557,"X":0,"Y":0},{"Time":17727,"X":1,"Y":2},{"Time":17898,"X":2,"Y":0},{"Time":18068,"X":0,"Y":1},{"Time":18239,"X":2,"Y":1},{"Time":18409,"X":0,"Y":2},{"Time":18580,"X":2,"Y":2},{"Time":18750,"X":0,"Y":1},{"Time":18921,"X":2,"Y":0},{"Time":19091,"X":1,"Y":2},{"Time":19261,"X":1,"Y":1},{"Time":19432,"X":0,"Y":0},{"Time":19602,"X":1,"Y":0},{"Time":19773,"X":1,"Y":1},{"Time":19943,"X":1,"Y":2},{"Time":20114,"X":2,"Y":2},{"Time":20284,"X":2,"Y":1},{"Time":20455,"X":2,"Y":0},{"Time":20625,"X":1,"Y":0},{"Time":20796,"X":0,"Y":0},{"Time":20966,"X":0,"Y":1},{"Time":21136,"X":0,"Y":2},{"Time":21307,"X":1,"Y":2},{"Time":21477,"X":2,"Y":2},{"Time":21648,"X":2.11,"Y":-0.109999895},{"Time":21648,"X":2,"Y":0},{"Time":21818,"X":-0.109999895,"Y":2.11},{"Time":21818,"X":0,"Y":2},{"Time":21989,"X":0,"Y":0},{"Time":21989,"X":-0.109999895,"Y":-0.109999895},{"Time":22159,"X":1,"Y":2},{"Time":22244,"X":2,"Y":0},{"Time":22330,"X":0,"Y":1},{"Time":22415,"X":2,"Y":2},{"Time":22500,"X":1,"Y":0},{"Time":22585,"X":0,"Y":2},{"Time":22671,"X":2,"Y":1},{"Time":22756,"X":0,"Y":0},{"Time":22841,"X":1,"Y":2},{"Time":23011,"X":1,"Y":0},{"Time":23097,"X":1,"Y":2},{"Time":23182,"X":0,"Y":0},{"Time":23352,"X":2,"Y":1},{"Time":23523,"X":0,"Y":2},{"Time":23693,"X":1,"Y":0},{"Time":23864,"X":1,"Y":2},{"Time":24034,"X":2,"Y":0},{"Time":24205,"X":2,"Y":2},{"Time":24375,"X":1,"Y":0},{"Time":24546,"X":0,"Y":2},{"Time":24716,"X":2,"Y":1},{"Time":24886,"X":0,"Y":0},{"Time":24972,"X":2,"Y":0},{"Time":25057,"X":0,"Y":1},{"Time":25142,"X":2,"Y":1},{"Time":25227,"X":0,"Y":2},{"Time":25313,"X":2,"Y":2},{"Time":25398,"X":0,"Y":1},{"Time":25483,"X":2,"Y":1},{"Time":25568,"X":0,"Y":0},{"Time":25739,"X":1,"Y":2},{"Time":25824,"X":1,"Y":0},{"Time":25909,"X":2,"Y":2},{"Time":26080,"X":0,"Y":1},{"Time":26250,"X":2,"Y":1},{"Time":26421,"X":0,"Y":2},{"Time":26591,"X":2,"Y":0},{"Time":26761,"X":1,"Y":2},{"Time":26932,"X":0,"Y":0},{"Time":27102,"X":2,"Y":1},{"Time":27273,"X":0,"Y":2},{"Time":27443,"X":1,"Y":0},{"Time":27614,"X":2,"Y":2},{"Time":27699,"X":2,"Y":0},{"Time":27784,"X":1,"Y":2},{"Time":27869,"X":1,"Y":0},{"Time":27955,"X":0,"Y":2},{"Time":28040,"X":0,"Y":0},{"Time":28125,"X":1,"Y":2},{"Time":28210,"X":1,"Y":0},{"Time":28296,"X":2,"Y":2},{"Time":28381,"X":0,"Y":1},{"Time":28466,"X":2,"Y":1},{"Time":28551,"X":0,"Y":2},{"Time":28636,"X":2,"Y":0},{"Time":28807,"X":0,"Y":0},{"Time":28977,"X":1,"Y":2},{"Time":29148,"X":1,"Y":0},{"Time":29318,"X":2,"Y":2},{"Time":29489,"X":0,"Y":0},{"Time":29659,"X":0,"Y":2},{"Time":29830,"X":1,"Y":0},{"Time":30000,"X":2,"Y":2},{"Time":30171,"X":0,"Y":1},{"Time":30341,"X":2,"Y":1},{"Time":30511,"X":0,"Y":2},{"Time":30597,"X":1,"Y":0},{"Time":30682,"X":1,"Y":2},{"Time":30767,"X":2,"Y":0},{"Time":30852,"X":2,"Y":2},{"Time":30938,"X":1,"Y":0},{"Time":31023,"X":1,"Y":2},{"Time":31108,"X":0,"Y":0},{"Time":31193,"X":0,"Y":2},{"Time":31278,"X":1,"Y":0},{"Time":31364,"X":2,"Y":2},{"Time":31534,"X":0,"Y":1},{"Time":31705,"X":2,"Y":1},{"Time":31875,"X":0,"Y":2},{"Time":32046,"X":2,"Y":0},{"Time":32216,"X":1,"Y":2},{"Time":32386,"X":0,"Y":0},{"Time":32386,"X":0,"Y":0.25},{"Time":32557,"X":2,"Y":1.75},{"Time":32557,"X":2,"Y":2},{"Time":32642,"X":-0.25,"Y":-0.25},{"Time":32642,"X":0,"Y":0},{"Time":32727,"X":2,"Y":1.25},{"Time":32727,"X":2,"Y":1},{"Time":32898,"X":0,"Y":0.75},{"Time":32898,"X":0,"Y":1},{"Time":33068,"X":2,"Y":2.25},{"Time":33068,"X":2,"Y":2},{"Time":33154,"X":0,"Y":0},{"Time":33239,"X":1,"Y":2},{"Time":33324,"X":1,"Y":0},{"Time":33409,"X":0,"Y":2},{"Time":33494,"X":2,"Y":0},{"Time":33580,"X":0,"Y":1},{"Time":33665,"X":2,"Y":1},{"Time":33750,"X":0,"Y":0},{"Time":33835,"X":2,"Y":2},{"Time":33921,"X":1,"Y":0},{"Time":34006,"X":1,"Y":2},{"Time":34091,"X":2,"Y":0},{"Time":34261,"X":0,"Y":2},{"Time":34432,"X":0,"Y":0},{"Time":34602,"X":1,"Y":2},{"Time":34773,"X":2,"Y":0},{"Time":34943,"X":0,"Y":1},{"Time":35114,"X":2,"Y":1},{"Time":35284,"X":0,"Y":2},{"Time":35455,"X":2,"Y":2},{"Time":35625,"X":0,"Y":1},{"Time":35796,"X":2,"Y":0},{"Time":35881,"X":1,"Y":2},{"Time":35966,"X":0,"Y":0},{"Time":36051,"X":0,"Y":2},{"Time":36136,"X":1,"Y":0},{"Time":36222,"X":2,"Y":2},{"Time":36307,"X":2,"Y":0},{"Time":36392,"X":1,"Y":2},{"Time":36477,"X":0,"Y":0},{"Time":36648,"X":2,"Y":1},{"Time":36733,"X":0,"Y":1},{"Time":36818,"X":2,"Y":0},{"Time":36989,"X":0,"Y":2},{"Time":37159,"X":1,"Y":0},{"Time":37330,"X":1,"Y":2},{"Time":37500,"X":0,"Y":0},{"Time":37671,"X":0,"Y":2},{"Time":37841,"X":1,"Y":0},{"Time":38011,"X":2,"Y":2},{"Time":38182,"X":0,"Y":1},{"Time":38352,"X":2,"Y":0},{"Time":38523,"X":1,"Y":2},{"Time":38608,"X":0,"Y":0},{"Time":38693,"X":2,"Y":1},{"Time":38778,"X":0,"Y":2},{"Time":38864,"X":1,"Y":0},{"Time":38949,"X":2,"Y":2},{"Time":39034,"X":0,"Y":1},{"Time":39119,"X":2,"Y":0},{"Time":39205,"X":1,"Y":2},{"Time":39290,"X":0,"Y":0},{"Time":39375,"X":2,"Y":1},{"Time":39460,"X":0,"Y":2},{"Time":39546,"X":1,"Y":0},{"Time":39716,"X":1,"Y":2},{"Time":39886,"X":2,"Y":0},{"Time":40057,"X":2,"Y":2},{"Time":40227,"X":1,"Y":0},{"Time":40398,"X":0,"Y":2},{"Time":40568,"X":2,"Y":1},{"Time":40739,"X":0,"Y":1},{"Time":40909,"X":2,"Y":0},{"Time":41080,"X":0,"Y":0},{"Time":41250,"X":2,"Y":1},{"Time":41335,"X":0,"Y":1},{"Time":41421,"X":2,"Y":2},{"Time":41506,"X":0,"Y":2},{"Time":41591,"X":2,"Y":1},{"Time":41676,"X":0,"Y":0},{"Time":41761,"X":1,"Y":2},{"Time":41847,"X":2,"Y":0},{"Time":41932,"X":0,"Y":1},{"Time":42102,"X":2,"Y":2},{"Time":42188,"X":1,"Y":0},{"Time":42273,"X":1,"Y":2},{"Time":42443,"X":0,"Y":0},{"Time":42614,"X":0,"Y":2},{"Time":42784,"X":1,"Y":0},{"Time":42955,"X":2,"Y":2},{"Time":43125,"X":0,"Y":1},{"Time":43296,"X":2,"Y":0},{"Time":43296,"X":2.25,"Y":-0.25},{"Time":43466,"X":1,"Y":2},{"Time":43466,"X":1,"Y":2.25},{"Time":43636,"X":-0.25,"Y":-0.25},{"Time":43636,"X":0,"Y":0},{"Time":43807,"X":2,"Y":1},{"Time":43977,"X":0,"Y":2},{"Time":44148,"X":2,"Y":2},{"Time":44318,"X":0,"Y":1},{"Time":44489,"X":2,"Y":0},{"Time":44659,"X":0,"Y":0},{"Time":44830,"X":2,"Y":1},{"Time":45000,"X":0,"Y":2},{"Time":45171,"X":1,"Y":0},{"Time":45341,"X":2,"Y":2},{"Time":45511,"X":0,"Y":1},{"Time":45682,"X":2,"Y":1},{"Time":45852,"X":0,"Y":2},{"Time":46023,"X":2,"Y":0},{"Time":46193,"X":1,"Y":2},{"Time":46364,"X":1,"Y":0},{"Time":46534,"X":2,"Y":2},{"Time":46705,"X":0,"Y":0},{"Time":46875,"X":2,"Y":1},{"Time":46960,"X":0,"Y":1},{"Time":47046,"X":2,"Y":2},{"Time":47216,"X":1,"Y":0},{"Time":47386,"X":0,"Y":2},{"Time":47428,"X":0.5,"Y":1.92},{"Time":47471,"X":0.96000004,"Y":1.7},{"Time":47514,"X":1.38,"Y":1.38},{"Time":47556,"X":1.7,"Y":0.96000004},{"Time":47599,"X":1.92,"Y":0.5},{"Time":47642,"X":2,"Y":0},{"Time":47898,"X":0,"Y":0},{"Time":47983,"X":1,"Y":2},{"Time":48068,"X":2,"Y":0},{"Time":48239,"X":0,"Y":1},{"Time":48409,"X":2,"Y":1},{"Time":48580,"X":0,"Y":2},{"Time":48750,"X":2,"Y":0},{"Time":48921,"X":1,"Y":2},{"Time":49091,"X":1,"Y":0},{"Time":49261,"X":2,"Y":2},{"Time":49432,"X":0,"Y":0},{"Time":49602,"X":2,"Y":1},{"Time":49773,"X":0,"Y":1},{"Time":49943,"X":2,"Y":0},{"Time":50114,"X":0,"Y":2},{"Time":50284,"X":1,"Y":0},{"Time":50455,"X":1,"Y":2},{"Time":50625,"X":0,"Y":0},{"Time":50796,"X":2,"Y":2},{"Time":50966,"X":0,"Y":1},{"Time":51136,"X":2,"Y":1},{"Time":51307,"X":0,"Y":2},{"Time":51477,"X":2,"Y":2},{"Time":51648,"X":0,"Y":1},{"Time":51818,"X":2,"Y":0},{"Time":51989,"X":1,"Y":2},{"Time":52159,"X":0,"Y":0},{"Time":52330,"X":0,"Y":2},{"Time":52500,"X":1,"Y":0},{"Time":52671,"X":2,"Y":2},{"Time":52841,"X":2,"Y":0},{"Time":52883,"X":1.92,"Y":0.5},{"Time":52926,"X":1.7,"Y":0.96000004},{"Time":52969,"X":1.38,"Y":1.38},{"Time":53011,"X":0.96000004,"Y":1.7},{"Time":53054,"X":0.5,"Y":1.92},{"Time":53097,"X":0,"Y":2},{"Time":53352,"X":0,"Y":0},{"Time":53438,"X":2,"Y":1},{"Time":53523,"X":0,"Y":2},{"Time":53693,"X":1,"Y":0},{"Time":53864,"X":1,"Y":2},{"Time":54034,"X":0,"Y":0},{"Time":54205,"X":2,"Y":2},{"Time":54375,"X":0,"Y":1},{"Time":54546,"X":2,"Y":1},{"Time":54716,"X":0,"Y":2},{"Time":54886,"X":2,"Y":2},{"Time":55057,"X":0,"Y":0},{"Time":55227,"X":2,"Y":1},{"Time":55398,"X":0,"Y":1},{"Time":55568,"X":2,"Y":2},{"Time":55739,"X":0,"Y":2},{"Time":55909,"X":2,"Y":1},{"Time":56080,"X":0,"Y":0},{"Time":56250,"X":1,"Y":2},{"Time":56421,"X":2,"Y":0},{"Time":56591,"X":0,"Y":1},{"Time":56761,"X":2,"Y":1},{"Time":56932,"X":0,"Y":2},{"Time":57102,"X":2,"Y":2},{"Time":57273,"X":0,"Y":1},{"Time":57443,"X":2,"Y":0},{"Time":57614,"X":1,"Y":2},{"Time":57784,"X":0,"Y":0},{"Time":57955,"X":2,"Y":1},{"Time":58125,"X":0,"Y":1},{"Time":58296,"X":2,"Y":2},{"Time":58466,"X":0,"Y":2},{"Time":58636,"X":2,"Y":1},{"Time":58807,"X":0,"Y":0},{"Time":58977,"X":1,"Y":2},{"Time":59148,"X":2,"Y":0},{"Time":59318,"X":0,"Y":1},{"Time":59489,"X":2,"Y":2},{"Time":59659,"X":1,"Y":0},{"Time":59830,"X":0,"Y":2},{"Time":60000,"X":2,"Y":1},{"Time":60171,"X":0,"Y":1},{"Time":60341,"X":2,"Y":0},{"Time":60384,"X":1,"Y":0},{"Time":60426,"X":0,"Y":0},{"Time":60469,"X":0,"Y":1},{"Time":60511,"X":1,"Y":1},{"Time":60554,"X":2,"Y":1},{"Time":60597,"X":2,"Y":2},{"Time":60639,"X":1,"Y":2},{"Time":60682,"X":0,"Y":2},{"Time":60725,"X":0,"Y":1},{"Time":60767,"X":0,"Y":0},{"Time":60810,"X":1,"Y":0},{"Time":60852,"X":1,"Y":1},{"Time":60895,"X":1,"Y":2},{"Time":60938,"X":2,"Y":2},{"Time":60980,"X":2,"Y":1},{"Time":61023,"X":2,"Y":0},{"Time":61065,"X":1,"Y":0},{"Time":61108,"X":0,"Y":0},{"Time":61151,"X":0,"Y":1},{"Time":61193,"X":1,"Y":1},{"Time":61236,"X":2,"Y":1},{"Time":61278,"X":2,"Y":2},{"Time":61321,"X":1,"Y":2},{"Time":61364,"X":0,"Y":2},{"Time":61406,"X":0,"Y":1},{"Time":61449,"X":0,"Y":0},{"Time":61492,"X":1,"Y":0},{"Time":61534,"X":2,"Y":0},{"Time":61577,"X":2,"Y":1},{"Time":61619,"X":2,"Y":2},{"Time":61662,"X":1,"Y":2},{"Time":61705,"X":0,"Y":2},{"Time":61747,"X":0,"Y":1},{"Time":61790,"X":1,"Y":1},{"Time":61832,"X":2,"Y":1},{"Time":61875,"X":2,"Y":0},{"Time":61918,"X":1,"Y":0},{"Time":61960,"X":0,"Y":0},{"Time":62003,"X":0,"Y":1},{"Time":62046,"X":0,"Y":2},{"Time":62088,"X":1,"Y":2},{"Time":62131,"X":2,"Y":2},{"Time":62173,"X":2,"Y":1},{"Time":62216,"X":2,"Y":0},{"Time":62259,"X":1,"Y":0},{"Time":62301,"X":1,"Y":1},{"Time":62344,"X":1,"Y":2},{"Time":62386,"X":0,"Y":2},{"Time":62429,"X":0,"Y":1},{"Time":62472,"X":0,"Y":0},{"Time":62514,"X":1,"Y":0},{"Time":62557,"X":2,"Y":0},{"Time":62600,"X":2,"Y":1},{"Time":62642,"X":1,"Y":1},{"Time":62685,"X":0,"Y":1},{"Time":62727,"X":0,"Y":2},{"Time":62770,"X":1,"Y":2},{"Time":62813,"X":2,"Y":2},{"Time":62855,"X":2,"Y":1},{"Time":62898,"X":2,"Y":0},{"Time":62940,"X":1,"Y":0},{"Time":62983,"X":0,"Y":0},{"Time":63026,"X":0,"Y":1},{"Time":63068,"X":0,"Y":2},{"Time":63111,"X":2,"Y":2},{"Time":63154,"X":2,"Y":1},{"Time":63196,"X":2,"Y":0},{"Time":63239,"X":1,"Y":0},{"Time":63281,"X":1,"Y":1},{"Time":63324,"X":1,"Y":2},{"Time":63367,"X":0,"Y":2},{"Time":63409,"X":0,"Y":1},{"Time":63452,"X":0,"Y":0},{"Time":63494,"X":1,"Y":0},{"Time":63537,"X":2,"Y":0},{"Time":63580,"X":2,"Y":1},{"Time":63622,"X":2,"Y":2},{"Time":63665,"X":1,"Y":2},{"Time":63707,"X":0,"Y":2},{"Time":63750,"X":0,"Y":1},{"Time":63793,"X":1,"Y":1},{"Time":63835,"X":2,"Y":1},{"Time":63878,"X":2,"Y":0},{"Time":63921,"X":1,"Y":0},{"Time":63963,"X":0,"Y":0},{"Time":64006,"X":0,"Y":1},{"Time":64048,"X":0,"Y":2},{"Time":64091,"X":1,"Y":2},{"Time":64134,"X":2,"Y":2},{"Time":64176,"X":2,"Y":1},{"Time":64219,"X":2,"Y":0},{"Time":64261,"X":1,"Y":0},{"Time":64304,"X":1,"Y":1},{"Time":64347,"X":1,"Y":2},{"Time":64389,"X":0,"Y":2},{"Time":64432,"X":0,"Y":1},{"Time":64475,"X":0,"Y":0},{"Time":64517,"X":1,"Y":0},{"Time":64560,"X":2,"Y":0},{"Time":64602,"X":2,"Y":1},{"Time":64645,"X":1,"Y":1},{"Time":64688,"X":0,"Y":1},{"Time":64730,"X":0,"Y":2},{"Time":64773,"X":1,"Y":2},{"Time":64815,"X":2,"Y":2},{"Time":64858,"X":2,"Y":1},{"Time":64901,"X":2,"Y":0},{"Time":64943,"X":1,"Y":0},{"Time":64986,"X":1,"Y":1},{"Time":65028,"X":1,"Y":2},{"Time":65071,"X":0,"Y":2},{"Time":65114,"X":0,"Y":1},{"Time":65156,"X":0,"Y":0},{"Time":65199,"X":1,"Y":0},{"Time":65242,"X":2,"Y":0},{"Time":65284,"X":2,"Y":1},{"Time":65327,"X":2,"Y":2},{"Time":65369,"X":1,"Y":2},{"Time":65412,"X":0,"Y":2},{"Time":65455,"X":0,"Y":1},{"Time":65497,"X":1,"Y":1},{"Time":65540,"X":2,"Y":1},{"Time":65582,"X":2,"Y":0},{"Time":65625,"X":1,"Y":0},{"Time":65668,"X":0,"Y":0},{"Time":65710,"X":0,"Y":1},{"Time":65753,"X":0,"Y":2},{"Time":65796,"X":1,"Y":2},{"Time":65838,"X":2,"Y":0},{"Time":65881,"X":1,"Y":0},{"Time":65923,"X":0,"Y":0},{"Time":65966,"X":0,"Y":1},{"Time":66009,"X":0,"Y":2},{"Time":66051,"X":1,"Y":2},{"Time":66094,"X":2,"Y":2},{"Time":66136,"X":2,"Y":1},{"Time":66179,"X":2,"Y":0},{"Time":66222,"X":1,"Y":0},{"Time":66264,"X":1,"Y":1},{"Time":66307,"X":1,"Y":2},{"Time":66350,"X":0,"Y":2},{"Time":66392,"X":0,"Y":1},{"Time":66435,"X":0,"Y":0},{"Time":66477,"X":1,"Y":0},{"Time":66520,"X":2,"Y":0},{"Time":66563,"X":2,"Y":1},{"Time":66605,"X":1,"Y":1},{"Time":66648,"X":0,"Y":1},{"Time":66690,"X":0,"Y":2},{"Time":66733,"X":1,"Y":2},{"Time":66776,"X":2,"Y":2},{"Time":66818,"X":2,"Y":1},{"Time":66861,"X":1,"Y":1},{"Time":66904,"X":0,"Y":1},{"Time":66946,"X":0,"Y":0},{"Time":66989,"X":1,"Y":0},{"Time":67031,"X":2,"Y":0},{"Time":67074,"X":2,"Y":1},{"Time":67117,"X":1,"Y":1},{"Time":67159,"X":0,"Y":1},{"Time":67202,"X":0,"Y":2},{"Time":67244,"X":1,"Y":2},{"Time":67287,"X":2,"Y":2},{"Time":67330,"X":2,"Y":1},{"Time":67372,"X":2,"Y":0},{"Time":67415,"X":1,"Y":0},{"Time":67457,"X":0,"Y":0},{"Time":67500,"X":0,"Y":1},{"Time":67543,"X":0,"Y":2},{"Time":67585,"X":1,"Y":2},{"Time":67628,"X":1,"Y":1},{"Time":67671,"X":1,"Y":0},{"Time":67713,"X":2,"Y":0},{"Time":67756,"X":2,"Y":1},{"Time":67798,"X":2,"Y":2},{"Time":67841,"X":1,"Y":2},{"Time":67884,"X":0,"Y":2},{"Time":67926,"X":0,"Y":1},{"Time":67969,"X":1,"Y":1},{"Time":68011,"X":2,"Y":1},{"Time":68054,"X":2,"Y":0},{"Time":68097,"X":1,"Y":0},{"Time":68139,"X":0,"Y":0},{"Time":68182,"X":0,"Y":1},{"Time":68225,"X":0,"Y":2},{"Time":68267,"X":1,"Y":2},{"Time":68310,"X":2,"Y":2},{"Time":68352,"X":2,"Y":1},{"Time":68395,"X":2,"Y":0},{"Time":68438,"X":1,"Y":0},{"Time":68480,"X":0,"Y":0},{"Time":68523,"X":0,"Y":1},{"Time":68565,"X":2,"Y":2},{"Time":68608,"X":2,"Y":1},{"Time":68651,"X":2,"Y":0},{"Time":68693,"X":1,"Y":0},{"Time":68736,"X":1,"Y":1},{"Time":68778,"X":1,"Y":2},{"Time":68821,"X":0,"Y":2},{"Time":68864,"X":0,"Y":1},{"Time":68906,"X":0,"Y":0},{"Time":68949,"X":1,"Y":0},{"Time":68992,"X":2,"Y":0},{"Time":69034,"X":2,"Y":1},{"Time":69077,"X":2,"Y":2},{"Time":69119,"X":1,"Y":2},{"Time":69162,"X":0,"Y":2},{"Time":69205,"X":0,"Y":1},{"Time":69247,"X":1,"Y":1},{"Time":69290,"X":2,"Y":1},{"Time":69332,"X":2,"Y":0},{"Time":69375,"X":1,"Y":0},{"Time":69418,"X":0,"Y":0},{"Time":69460,"X":0,"Y":1},{"Time":69503,"X":0,"Y":2},{"Time":69546,"X":1,"Y":2},{"Time":69588,"X":2,"Y":2},{"Time":69631,"X":2,"Y":1},{"Time":69673,"X":2,"Y":0},{"Time":69716,"X":1,"Y":0},{"Time":69759,"X":1,"Y":1},{"Time":69801,"X":1,"Y":2},{"Time":69844,"X":0,"Y":2},{"Time":69886,"X":0,"Y":1},{"Time":70057,"X":2,"Y":2},{"Time":70227,"X":0,"Y":2},{"Time":70398,"X":2,"Y":1},{"Time":70568,"X":0,"Y":1},{"Time":70739,"X":2,"Y":0},{"Time":70909,"X":0,"Y":0},{"Time":71080,"X":2,"Y":1},{"Time":71250,"X":0,"Y":1},{"Time":71421,"X":2,"Y":2},{"Time":71761,"X":1,"Y":0},{"Time":71932,"X":0,"Y":2},{"Time":71975,"X":0,"Y":1},{"Time":72017,"X":0,"Y":0},{"Time":72102,"X":1,"Y":2},{"Time":72145,"X":1,"Y":1},{"Time":72188,"X":1,"Y":0},{"Time":72273,"X":2,"Y":2},{"Time":72315,"X":2,"Y":1},{"Time":72358,"X":2,"Y":0},{"Time":72443,"X":1,"Y":2},{"Time":72486,"X":1,"Y":1},{"Time":72528,"X":1,"Y":0},{"Time":72614,"X":0,"Y":2},{"Time":72656,"X":0,"Y":1},{"Time":72699,"X":0,"Y":0},{"Time":72784,"X":2,"Y":2},{"Time":73125,"X":0,"Y":1},{"Time":73296,"X":2,"Y":0},{"Time":73338,"X":1,"Y":0},{"Time":73381,"X":0,"Y":0},{"Time":73466,"X":2,"Y":1},{"Time":73509,"X":1,"Y":1},{"Time":73551,"X":0,"Y":1},{"Time":73636,"X":2,"Y":2},{"Time":73679,"X":1,"Y":2},{"Time":73722,"X":0,"Y":2},{"Time":73807,"X":2,"Y":1},{"Time":73850,"X":1,"Y":1},{"Time":73892,"X":0,"Y":1},{"Time":73977,"X":2,"Y":0},{"Time":74020,"X":1,"Y":0},{"Time":74063,"X":0,"Y":0},{"Time":74148,"X":0,"Y":2},{"Time":74318,"X":2,"Y":2},{"Time":74489,"X":2,"Y":0},{"Time":74659,"X":0,"Y":2},{"Time":74830,"X":0,"Y":0},{"Time":75000,"X":1,"Y":2},{"Time":75171,"X":2,"Y":0},{"Time":75341,"X":2,"Y":2},{"Time":75384,"X":2,"Y":1},{"Time":75426,"X":2,"Y":0},{"Time":75511,"X":0,"Y":2},{"Time":75554,"X":1,"Y":2},{"Time":75597,"X":2,"Y":2},{"Time":75682,"X":0,"Y":0},{"Time":75725,"X":0,"Y":1},{"Time":75767,"X":0,"Y":2},{"Time":75852,"X":2,"Y":0},{"Time":75895,"X":1,"Y":0},{"Time":75938,"X":0,"Y":0},{"Time":76023,"X":2,"Y":2},{"Time":76065,"X":2,"Y":1},{"Time":76108,"X":2,"Y":0},{"Time":76193,"X":0,"Y":2},{"Time":76364,"X":2,"Y":0},{"Time":76534,"X":0,"Y":2},{"Time":76705,"X":1,"Y":0},{"Time":76875,"X":1,"Y":2},{"Time":77045,"X":2,"Y":0},{"Time":77216,"X":0,"Y":0},{"Time":77386,"X":2,"Y":2},{"Time":77429,"X":2,"Y":1},{"Time":77472,"X":2,"Y":0},{"Time":77557,"X":0,"Y":2},{"Time":77600,"X":0,"Y":1},{"Time":77642,"X":0,"Y":0},{"Time":77727,"X":2,"Y":2},{"Time":77770,"X":2,"Y":1},{"Time":77813,"X":2,"Y":0},{"Time":77898,"X":0,"Y":2},{"Time":77940,"X":0,"Y":1},{"Time":77983,"X":0,"Y":0},{"Time":78068,"X":2,"Y":2},{"Time":78111,"X":2,"Y":1},{"Time":78154,"X":2,"Y":0},{"Time":78239,"X":0,"Y":0},{"Time":78409,"X":0,"Y":2},{"Time":78580,"X":2,"Y":1},{"Time":78750,"X":0,"Y":0},{"Time":78793,"X":1,"Y":0},{"Time":78835,"X":2,"Y":0},{"Time":78921,"X":0,"Y":2},{"Time":78963,"X":1,"Y":2},{"Time":79006,"X":2,"Y":2},{"Time":79091,"X":0,"Y":0},{"Time":79134,"X":1,"Y":0},{"Time":79176,"X":2,"Y":0},{"Time":79261,"X":0,"Y":2},{"Time":79304,"X":1,"Y":2},{"Time":79347,"X":2,"Y":2},{"Time":79432,"X":0,"Y":0},{"Time":79475,"X":1,"Y":0},{"Time":79517,"X":2,"Y":0},{"Time":79602,"X":2,"Y":2},{"Time":79773,"X":0,"Y":2},{"Time":79943,"X":1,"Y":0},{"Time":80114,"X":2,"Y":2},{"Time":80284,"X":0,"Y":1},{"Time":80455,"X":2,"Y":0},{"Time":80625,"X":1,"Y":2},{"Time":80796,"X":0,"Y":0},{"Time":80838,"X":0,"Y":1},{"Time":80881,"X":0,"Y":2},{"Time":80966,"X":2,"Y":0},{"Time":81009,"X":1,"Y":0},{"Time":81051,"X":0,"Y":0},{"Time":81136,"X":2,"Y":2},{"Time":81179,"X":1,"Y":2},{"Time":81222,"X":0,"Y":2},{"Time":81307,"X":2,"Y":0},{"Time":81350,"X":2,"Y":1},{"Time":81392,"X":2,"Y":2},{"Time":81477,"X":0,"Y":1},{"Time":81520,"X":1,"Y":1},{"Time":81563,"X":2,"Y":1},{"Time":81648,"X":0,"Y":2},{"Time":81818,"X":2,"Y":2},{"Time":81989,"X":0,"Y":1},{"Time":82159,"X":2,"Y":0},{"Time":82330,"X":1,"Y":2},{"Time":82500,"X":0,"Y":0},{"Time":82671,"X":2,"Y":1},{"Time":82841,"X":0,"Y":1},{"Time":82884,"X":1,"Y":1},{"Time":82926,"X":2,"Y":1},{"Time":83011,"X":0,"Y":2},{"Time":83054,"X":1,"Y":2},{"Time":83097,"X":2,"Y":2},{"Time":83182,"X":0,"Y":0},{"Time":83225,"X":0,"Y":1},{"Time":83267,"X":0,"Y":2},{"Time":83352,"X":2,"Y":0},{"Time":83395,"X":2,"Y":1},{"Time":83438,"X":2,"Y":2},{"Time":83523,"X":0,"Y":0},{"Time":83565,"X":1,"Y":0},{"Time":83608,"X":2,"Y":0},{"Time":83693,"X":2,"Y":2},{"Time":83864,"X":0,"Y":2},{"Time":84034,"X":0,"Y":0},{"Time":84205,"X":1,"Y":2},{"Time":84247,"X":1,"Y":1},{"Time":84290,"X":1,"Y":0},{"Time":84375,"X":2,"Y":2},{"Time":84418,"X":2,"Y":1},{"Time":84460,"X":2,"Y":0},{"Time":84546,"X":0,"Y":2},{"Time":84588,"X":0,"Y":1},{"Time":84631,"X":0,"Y":0},{"Time":84716,"X":1,"Y":2},{"Time":84759,"X":1,"Y":1},{"Time":84801,"X":1,"Y":0},{"Time":84886,"X":0,"Y":2},{"Time":84929,"X":1,"Y":2},{"Time":84972,"X":2,"Y":2},{"Time":85057,"X":2,"Y":0},{"Time":85227,"X":0,"Y":0},{"Time":85398,"X":1,"Y":2},{"Time":85568,"X":2,"Y":0},{"Time":85739,"X":0,"Y":1},{"Time":85909,"X":2,"Y":2},{"Time":86080,"X":0,"Y":2},{"Time":86250,"X":2,"Y":0},{"Time":86293,"X":2,"Y":1},{"Time":86335,"X":2,"Y":2},{"Time":86421,"X":0,"Y":0},{"Time":86463,"X":0,"Y":1},{"Time":86506,"X":0,"Y":2},{"Time":86591,"X":2,"Y":0},{"Time":86634,"X":1,"Y":0},{"Time":86676,"X":0,"Y":0},{"Time":86761,"X":2,"Y":2},{"Time":86804,"X":1,"Y":2},{"Time":86847,"X":0,"Y":2},{"Time":86932,"X":2,"Y":0},{"Time":86975,"X":2,"Y":1},{"Time":87017,"X":2,"Y":2},{"Time":87102,"X":0,"Y":2},{"Time":87273,"X":0,"Y":0},{"Time":87443,"X":2,"Y":1},{"Time":87614,"X":0,"Y":2},{"Time":87784,"X":1,"Y":0},{"Time":87955,"X":1,"Y":2},{"Time":88125,"X":0,"Y":0},{"Time":88296,"X":2,"Y":2},{"Time":88338,"X":2,"Y":1},{"Time":88381,"X":2,"Y":0},{"Time":88466,"X":1,"Y":2},{"Time":88509,"X":1,"Y":1},{"Time":88551,"X":1,"Y":0},{"Time":88636,"X":0,"Y":2},{"Time":88679,"X":0,"Y":1},{"Time":88722,"X":0,"Y":0},{"Time":88807,"X":1,"Y":2},{"Time":88850,"X":1,"Y":1},{"Time":88892,"X":1,"Y":0},{"Time":88977,"X":2,"Y":2},{"Time":89020,"X":2,"Y":1},{"Time":89063,"X":2,"Y":0},{"Time":89148,"X":0,"Y":0},{"Time":89318,"X":0,"Y":2},{"Time":89489,"X":2,"Y":1},{"Time":89659,"X":0,"Y":0},{"Time":89702,"X":0,"Y":1},{"Time":89744,"X":0,"Y":2},{"Time":89830,"X":2,"Y":2},{"Time":89872,"X":1,"Y":2},{"Time":89915,"X":0,"Y":2},{"Time":90000,"X":2,"Y":0},{"Time":90043,"X":1,"Y":0},{"Time":90085,"X":0,"Y":0},{"Time":90171,"X":2,"Y":2},{"Time":90213,"X":2,"Y":1},{"Time":90256,"X":2,"Y":0},{"Time":90341,"X":0,"Y":1},{"Time":90384,"X":1,"Y":1},{"Time":90426,"X":2,"Y":1},{"Time":90511,"X":0,"Y":2},{"Time":90682,"X":2,"Y":2},{"Time":90852,"X":0,"Y":1},{"Time":91023,"X":2,"Y":0},{"Time":91193,"X":1,"Y":2},{"Time":91364,"X":0,"Y":0},{"Time":91534,"X":2,"Y":1},{"Time":91705,"X":0,"Y":2},{"Time":91790,"X":1,"Y":0},{"Time":91875,"X":1,"Y":2},{"Time":91960,"X":2,"Y":0},{"Time":92046,"X":0,"Y":1},{"Time":92131,"X":2,"Y":1},{"Time":92216,"X":0,"Y":2},{"Time":92301,"X":2,"Y":2},{"Time":92386,"X":0,"Y":0},{"Time":92472,"X":0,"Y":2},{"Time":92557,"X":1,"Y":0},{"Time":92642,"X":2,"Y":2},{"Time":92727,"X":0,"Y":1},{"Time":92813,"X":2,"Y":1},{"Time":92898,"X":0,"Y":2},{"Time":92983,"X":2,"Y":2},{"Time":93068,"X":0,"Y":1},{"Time":93154,"X":2,"Y":0},{"Time":93239,"X":1,"Y":2},{"Time":93324,"X":0,"Y":0},{"Time":93409,"X":2,"Y":1},{"Time":93494,"X":0,"Y":2},{"Time":93580,"X":1,"Y":0},{"Time":93665,"X":2,"Y":2},{"Time":93750,"X":0,"Y":0},{"Time":93835,"X":2,"Y":0},{"Time":93921,"X":0,"Y":1},{"Time":94006,"X":2,"Y":1},{"Time":94091,"X":0,"Y":2},{"Time":94176,"X":2,"Y":2},{"Time":94261,"X":0,"Y":1},{"Time":94347,"X":2,"Y":1},{"Time":94432,"X":0,"Y":0},{"Time":94517,"X":2,"Y":0},{"Time":94602,"X":0,"Y":1},{"Time":94688,"X":2,"Y":1},{"Time":94773,"X":0,"Y":2},{"Time":94858,"X":2,"Y":2},{"Time":94943,"X":0,"Y":1},{"Time":95028,"X":2,"Y":1},{"Time":95114,"X":0,"Y":0},{"Time":95199,"X":2,"Y":0},{"Time":95284,"X":0,"Y":1},{"Time":95369,"X":2,"Y":1},{"Time":95455,"X":0,"Y":2},{"Time":95540,"X":2,"Y":2},{"Time":95625,"X":0,"Y":1},{"Time":95710,"X":2,"Y":1},{"Time":95796,"X":0,"Y":0},{"Time":95881,"X":2,"Y":2},{"Time":95966,"X":1,"Y":0},{"Time":96051,"X":1,"Y":2},{"Time":96136,"X":2,"Y":0},{"Time":96222,"X":0,"Y":2},{"Time":96307,"X":2,"Y":1},{"Time":96392,"X":0,"Y":1},{"Time":96477,"X":2,"Y":2},{"Time":96563,"X":0,"Y":0},{"Time":96648,"X":1,"Y":2},{"Time":96733,"X":1,"Y":0},{"Time":96818,"X":0,"Y":2},{"Time":96904,"X":2,"Y":0},{"Time":96989,"X":0,"Y":1},{"Time":97074,"X":2,"Y":1},{"Time":97159,"X":0,"Y":0},{"Time":97244,"X":2,"Y":2},{"Time":97330,"X":1,"Y":0},{"Time":97415,"X":1,"Y":2},{"Time":97500,"X":2,"Y":0},{"Time":97585,"X":0,"Y":2},{"Time":97671,"X":2,"Y":1},{"Time":97756,"X":0,"Y":1},{"Time":97841,"X":2,"Y":2},{"Time":97926,"X":0,"Y":0},{"Time":98011,"X":1,"Y":2},{"Time":98097,"X":1,"Y":0},{"Time":98182,"X":0,"Y":2},{"Time":98267,"X":2,"Y":0},{"Time":98352,"X":0,"Y":1},{"Time":98438,"X":2,"Y":1},{"Time":98523,"X":0,"Y":0},{"Time":98608,"X":0,"Y":2},{"Time":98693,"X":1,"Y":0},{"Time":98778,"X":2,"Y":2},{"Time":98864,"X":0,"Y":1},{"Time":98949,"X":2,"Y":0},{"Time":99034,"X":1,"Y":2},{"Time":99119,"X":0,"Y":0},{"Time":99205,"X":2,"Y":1},{"Time":99290,"X":0,"Y":2},{"Time":99375,"X":1,"Y":0},{"Time":99460,"X":2,"Y":2},{"Time":99546,"X":0,"Y":1},{"Time":99631,"X":2,"Y":0},{"Time":99716,"X":1,"Y":2},{"Time":99801,"X":0,"Y":0},{"Time":99886,"X":2,"Y":1},{"Time":99972,"X":0,"Y":2},{"Time":100057,"X":1,"Y":0},{"Time":100142,"X":2,"Y":2},{"Time":100227,"X":0,"Y":1},{"Time":100313,"X":2,"Y":0},{"Time":100398,"X":1,"Y":2},{"Time":100483,"X":0,"Y":0},{"Time":100568,"X":2,"Y":1},{"Time":100654,"X":0,"Y":2},{"Time":100739,"X":1,"Y":0},{"Time":100824,"X":2,"Y":2},{"Time":100909,"X":0,"Y":1},{"Time":100994,"X":2,"Y":0},{"Time":101080,"X":1,"Y":2},{"Time":101165,"X":0,"Y":0},{"Time":101250,"X":2,"Y":1},{"Time":101335,"X":0,"Y":1},{"Time":101421,"X":2,"Y":2},{"Time":101506,"X":0,"Y":2},{"Time":101591,"X":2,"Y":1},{"Time":101676,"X":0,"Y":0},{"Time":101761,"X":1,"Y":2},{"Time":101847,"X":2,"Y":0},{"Time":101932,"X":0,"Y":1},{"Time":102017,"X":2,"Y":2},{"Time":102102,"X":1,"Y":0},{"Time":102188,"X":0,"Y":2},{"Time":102273,"X":2,"Y":1},{"Time":102358,"X":0,"Y":1},{"Time":102443,"X":2,"Y":0},{"Time":102528,"X":0,"Y":0},{"Time":102614,"X":2,"Y":1},{"Time":102699,"X":0,"Y":2},{"Time":102784,"X":1,"Y":0},{"Time":102869,"X":2,"Y":2},{"Time":102955,"X":0,"Y":1},{"Time":103040,"X":2,"Y":0},{"Time":103125,"X":1,"Y":2},{"Time":103210,"X":0,"Y":0},{"Time":103296,"X":2,"Y":1},{"Time":103381,"X":0,"Y":2},{"Time":103466,"X":1,"Y":0},{"Time":103551,"X":2,"Y":2},{"Time":103636,"X":0,"Y":1},{"Time":103722,"X":2,"Y":1},{"Time":103807,"X":0,"Y":2},{"Time":103892,"X":2,"Y":0},{"Time":103977,"X":1,"Y":2},{"Time":104063,"X":1,"Y":0},{"Time":104148,"X":0,"Y":2},{"Time":104233,"X":0,"Y":0},{"Time":104318,"X":2,"Y":2},{"Time":104404,"X":2,"Y":0},{"Time":104489,"X":1,"Y":2},{"Time":104574,"X":1,"Y":0},{"Time":104659,"X":0,"Y":2},{"Time":104744,"X":0,"Y":0},{"Time":104830,"X":2,"Y":2},{"Time":104915,"X":2,"Y":0},{"Time":105000,"X":1,"Y":2},{"Time":105085,"X":1,"Y":0},{"Time":105171,"X":0,"Y":2},{"Time":105256,"X":0,"Y":0},{"Time":105341,"X":2,"Y":2},{"Time":105426,"X":2,"Y":0},{"Time":105511,"X":1,"Y":2},{"Time":105597,"X":1,"Y":0},{"Time":105682,"X":0,"Y":2},{"Time":105767,"X":0,"Y":0},{"Time":105852,"X":2,"Y":2},{"Time":105938,"X":2,"Y":0},{"Time":106023,"X":1,"Y":2},{"Time":106108,"X":1,"Y":0},{"Time":106193,"X":0,"Y":2},{"Time":106278,"X":0,"Y":0},{"Time":106364,"X":2,"Y":2},{"Time":106449,"X":2,"Y":0},{"Time":106534,"X":1,"Y":2},{"Time":106619,"X":1,"Y":0},{"Time":106705,"X":0,"Y":2},{"Time":106790,"X":2,"Y":1},{"Time":106875,"X":0,"Y":1},{"Time":106960,"X":2,"Y":2},{"Time":107046,"X":0,"Y":0},{"Time":107131,"X":1,"Y":2},{"Time":107216,"X":1,"Y":0},{"Time":107301,"X":0,"Y":2},{"Time":107386,"X":2,"Y":0},{"Time":107472,"X":0,"Y":1},{"Time":107557,"X":2,"Y":1},{"Time":107642,"X":0,"Y":0},{"Time":107727,"X":2,"Y":2},{"Time":107813,"X":1,"Y":0},{"Time":107898,"X":0,"Y":2},{"Time":107983,"X":2,"Y":1},{"Time":108068,"X":0,"Y":1},{"Time":108154,"X":2,"Y":2},{"Time":108239,"X":1,"Y":0},{"Time":108324,"X":0,"Y":2},{"Time":108409,"X":2,"Y":1},{"Time":108494,"X":0,"Y":1},{"Time":108580,"X":2,"Y":2},{"Time":108665,"X":1,"Y":0},{"Time":108750,"X":0,"Y":2},{"Time":108835,"X":2,"Y":1},{"Time":108921,"X":0,"Y":1},{"Time":109006,"X":2,"Y":2},{"Time":109091,"X":1,"Y":0},{"Time":109176,"X":0,"Y":2},{"Time":109261,"X":2,"Y":1},{"Time":109347,"X":0,"Y":1},{"Time":109432,"X":2,"Y":2},{"Time":109517,"X":0,"Y":0},{"Time":109602,"X":1,"Y":2},{"Time":109688,"X":1,"Y":0},{"Time":109773,"X":0,"Y":2},{"Time":109858,"X":2,"Y":0},{"Time":109943,"X":0,"Y":1},{"Time":110028,"X":2,"Y":1},{"Time":110114,"X":0,"Y":0},{"Time":110199,"X":2,"Y":2},{"Time":110284,"X":1,"Y":0},{"Time":110369,"X":1,"Y":2},{"Time":110455,"X":2,"Y":0},{"Time":110540,"X":0,"Y":2},{"Time":110625,"X":2,"Y":1},{"Time":110710,"X":0,"Y":1},{"Time":110796,"X":2,"Y":2},{"Time":110881,"X":0,"Y":0},{"Time":110966,"X":1,"Y":2},{"Time":111051,"X":1,"Y":0},{"Time":111136,"X":0,"Y":2},{"Time":111222,"X":2,"Y":0},{"Time":111307,"X":0,"Y":1},{"Time":111392,"X":2,"Y":1},{"Time":111477,"X":0,"Y":0},{"Time":111563,"X":2,"Y":2},{"Time":111648,"X":1,"Y":0},{"Time":111733,"X":1,"Y":2},{"Time":111818,"X":2,"Y":0},{"Time":111904,"X":0,"Y":2},{"Time":111989,"X":2,"Y":1},{"Time":112074,"X":0,"Y":1},{"Time":112159,"X":2,"Y":2},{"Time":112244,"X":0,"Y":2},{"Time":112330,"X":2,"Y":1},{"Time":112415,"X":0,"Y":1},{"Time":112500,"X":2,"Y":0},{"Time":112585,"X":0,"Y":0},{"Time":112671,"X":2,"Y":1},{"Time":112756,"X":0,"Y":1},{"Time":112841,"X":2,"Y":2},{"Time":112926,"X":0,"Y":2},{"Time":113011,"X":2,"Y":1},{"Time":113097,"X":0,"Y":1},{"Time":113182,"X":2,"Y":0},{"Time":113267,"X":0,"Y":0},{"Time":113352,"X":2,"Y":1},{"Time":113438,"X":0,"Y":1},{"Time":113523,"X":2,"Y":2},{"Time":113636,"X":0,"Y":1},{"Time":113750,"X":2,"Y":0},{"Time":113864,"X":1,"Y":2},{"Time":113977,"X":0,"Y":0},{"Time":114091,"X":2,"Y":1},{"Time":114205,"X":0,"Y":2},{"Time":114318,"X":1,"Y":0},{"Time":114432,"X":2,"Y":2},{"Time":114546,"X":0,"Y":1},{"Time":114659,"X":2,"Y":1},{"Time":114773,"X":0,"Y":2},{"Time":114886,"X":2,"Y":0},{"Time":115000,"X":1,"Y":2},{"Time":115114,"X":1,"Y":0},{"Time":115227,"X":2,"Y":2},{"Time":115341,"X":0,"Y":0},{"Time":115455,"X":0,"Y":2},{"Time":115568,"X":1,"Y":0},{"Time":115682,"X":2,"Y":2},{"Time":115796,"X":0,"Y":1},{"Time":115909,"X":2,"Y":1},{"Time":116023,"X":0,"Y":2},{"Time":116136,"X":1,"Y":0},{"Time":116250,"X":1,"Y":2},{"Time":116364,"X":2,"Y":0},{"Time":116477,"X":0,"Y":1},{"Time":116591,"X":2,"Y":1},{"Time":116705,"X":0,"Y":0},{"Time":116818,"X":0,"Y":2},{"Time":116932,"X":2,"Y":0},{"Time":117046,"X":0,"Y":1},{"Time":117159,"X":2,"Y":2},{"Time":117273,"X":0,"Y":0},{"Time":117386,"X":0,"Y":2},{"Time":117500,"X":2,"Y":0},{"Time":117614,"X":0,"Y":1},{"Time":117727,"X":2,"Y":1},{"Time":117841,"X":0,"Y":2},{"Time":117955,"X":1,"Y":0},{"Time":118068,"X":2,"Y":2},{"Time":118182,"X":0,"Y":1},{"Time":118296,"X":2.05,"Y":-0.049999952},{"Time":118409,"X":1,"Y":2.1},{"Time":118523,"X":-0.16000009,"Y":-0.16000009},{"Time":118636,"X":2.22,"Y":1},{"Time":118750,"X":-0.25,"Y":2.25},{"Time":118864,"X":1,"Y":-0.29999995},{"Time":118977,"X":2.35,"Y":2.35},{"Time":119091,"X":-0.29999995,"Y":1},{"Time":119205,"X":2.25,"Y":-0.25},{"Time":119318,"X":2.2,"Y":2.2},{"Time":119432,"X":-0.1500001,"Y":-0.1500001},{"Time":119546,"X":-0.099999905,"Y":2.1},{"Time":119659,"X":2,"Y":1},{"Time":119773,"X":0,"Y":1},{"Time":119886,"X":2.05,"Y":2.05},{"Time":120000,"X":1,"Y":-0.099999905},{"Time":120114,"X":-0.1500001,"Y":2.15},{"Time":120227,"X":2.1,"Y":1},{"Time":120341,"X":-0.049999952,"Y":1},{"Time":120455,"X":2.05,"Y":2.05},{"Time":120568,"X":-0.099999905,"Y":-0.099999905},{"Time":120682,"X":2.16,"Y":-0.16000009},{"Time":120796,"X":-0.22000003,"Y":2.22},{"Time":120909,"X":2.28,"Y":2.28},{"Time":121023,"X":1,"Y":-0.3399999},{"Time":121136,"X":1,"Y":2.48},{"Time":121250,"X":-0.45000005,"Y":-0.45000005},{"Time":121364,"X":2.5,"Y":2.5},{"Time":121477,"X":-0.51,"Y":1},{"Time":121591,"X":2.52,"Y":1},{"Time":121705,"X":-0.53,"Y":2.53},{"Time":121818,"X":2,"Y":0},{"Time":121932,"X":1,"Y":2.12},{"Time":122046,"X":-0.099999905,"Y":-0.099999905},{"Time":122159,"X":2.15,"Y":1},{"Time":122273,"X":-0.20000005,"Y":1},{"Time":122386,"X":2.25,"Y":2.25},{"Time":122500,"X":-0.29999995,"Y":2.3},{"Time":122614,"X":2.35,"Y":1},{"Time":122727,"X":-0.4000001,"Y":1},{"Time":122841,"X":2.45,"Y":-0.45000005},{"Time":122955,"X":-0.5,"Y":-0.5},{"Time":123068,"X":2.52,"Y":1},{"Time":123182,"X":-0.5,"Y":2.5},{"Time":123296,"X":1,"Y":-0.45000005},{"Time":123409,"X":2.4,"Y":2.4},{"Time":123523,"X":-0.3499999,"Y":1},{"Time":123636,"X":2.3,"Y":-0.29999995},{"Time":123750,"X":1,"Y":2.25},{"Time":123864,"X":-0.20000005,"Y":-0.20000005},{"Time":123977,"X":2.15,"Y":1},{"Time":124091,"X":-0.099999905,"Y":2.1},{"Time":124205,"X":1,"Y":-0.049999952},{"Time":124318,"X":2,"Y":2},{"Time":124432,"X":0.01999998,"Y":1},{"Time":124546,"X":1.95,"Y":1},{"Time":124659,"X":0.08000004,"Y":1.93},{"Time":124773,"X":1.9,"Y":0.100000024},{"Time":124886,"X":1,"Y":1.9},{"Time":125000,"X":0.100000024,"Y":0.100000024},{"Time":125114,"X":1.9,"Y":1},{"Time":125227,"X":0.100000024,"Y":1.9},{"Time":125341,"X":1,"Y":0.100000024},{"Time":125455,"X":1.9,"Y":1.9},{"Time":125568,"X":0.100000024,"Y":1},{"Time":125682,"X":1.9,"Y":0.100000024},{"Time":125796,"X":1,"Y":1.83},{"Time":125909,"X":0.049999952,"Y":0.049999952},{"Time":126023,"X":1.98,"Y":1},{"Time":126136,"X":0,"Y":2},{"Time":126250,"X":1,"Y":-0.049999952},{"Time":126364,"X":1,"Y":2.1},{"Time":126477,"X":2.15,"Y":-0.1500001},{"Time":126591,"X":2.2,"Y":2.2},{"Time":126705,"X":1,"Y":-0.25},{"Time":126818,"X":-0.29999995,"Y":2.3},{"Time":126932,"X":2.25,"Y":1},{"Time":127046,"X":-0.20000005,"Y":-0.20000005},{"Time":127159,"X":1,"Y":2.15},{"Time":127273,"X":1,"Y":-0.099999905},{"Time":127386,"X":2.15,"Y":2.15},{"Time":127500,"X":-0.20000005,"Y":-0.20000005},{"Time":127614,"X":2.25,"Y":1},{"Time":127727,"X":-0.29999995,"Y":1},{"Time":127841,"X":2.35,"Y":-0.3499999},{"Time":127955,"X":1,"Y":2.4},{"Time":128068,"X":-0.45000005,"Y":-0.45000005},{"Time":128182,"X":2.4,"Y":1},{"Time":128296,"X":-0.3499999,"Y":1},{"Time":128409,"X":2,"Y":2},{"Time":128523,"X":0,"Y":2},{"Time":128636,"X":1,"Y":0},{"Time":128753,"X":1,"Y":2},{"Time":128870,"X":1,"Y":0},{"Time":128987,"X":2,"Y":2},{"Time":129104,"X":2,"Y":0},{"Time":129221,"X":2,"Y":2},{"Time":129338,"X":0,"Y":0},{"Time":129455,"X":0,"Y":2},{"Time":129572,"X":0,"Y":0},{"Time":129689,"X":2,"Y":1},{"Time":129806,"X":0,"Y":1},{"Time":129923,"X":2,"Y":1},{"Time":130040,"X":0,"Y":2},{"Time":130156,"X":2,"Y":2},{"Time":130273,"X":0,"Y":2},{"Time":130390,"X":1,"Y":0},{"Time":130507,"X":1,"Y":2},{"Time":130624,"X":1,"Y":0},{"Time":130741,"X":2,"Y":2},{"Time":130858,"X":2,"Y":0},{"Time":130975,"X":2,"Y":2},{"Time":131092,"X":0,"Y":1},{"Time":131209,"X":2,"Y":1},{"Time":131326,"X":0,"Y":1},{"Time":131443,"X":2,"Y":0},{"Time":131560,"X":2,"Y":2},{"Time":131677,"X":2,"Y":0},{"Time":131794,"X":0,"Y":1},{"Time":131911,"X":2,"Y":1},{"Time":132028,"X":0,"Y":1},{"Time":132145,"X":2,"Y":0},{"Time":132262,"X":2,"Y":2},{"Time":132379,"X":2,"Y":0},{"Time":132496,"X":0,"Y":2},{"Time":132613,"X":0,"Y":0},{"Time":132730,"X":2,"Y":2},{"Time":132847,"X":1,"Y":0},{"Time":132963,"X":0,"Y":2},{"Time":133080,"X":1,"Y":0},{"Time":133197,"X":2,"Y":2},{"Time":133314,"X":0,"Y":1},{"Time":133431,"X":2,"Y":2},{"Time":133548,"X":1,"Y":0},{"Time":133665,"X":1,"Y":2},{"Time":133782,"X":1,"Y":0},{"Time":133899,"X":0,"Y":2},{"Time":134016,"X":2,"Y":1},{"Time":134133,"X":0,"Y":2},{"Time":134250,"X":2,"Y":1},{"Time":134367,"X":0,"Y":1},{"Time":134484,"X":2,"Y":0},{"Time":134601,"X":0,"Y":0},{"Time":134718,"X":2,"Y":1},{"Time":134835,"X":0,"Y":1},{"Time":134952,"X":2,"Y":2},{"Time":135069,"X":0,"Y":1},{"Time":135186,"X":2,"Y":0},{"Time":135303,"X":1,"Y":2},{"Time":135420,"X":0,"Y":0},{"Time":135537,"X":2,"Y":1},{"Time":135654,"X":0,"Y":2},{"Time":135774,"X":1,"Y":0},{"Time":135895,"X":1,"Y":2},{"Time":136015,"X":1,"Y":0},{"Time":136136,"X":0,"Y":2},{"Time":136256,"X":0,"Y":0},{"Time":136377,"X":0,"Y":2},{"Time":136497,"X":2,"Y":0},{"Time":136618,"X":0,"Y":0},{"Time":136738,"X":2,"Y":0},{"Time":136859,"X":0,"Y":1},{"Time":136979,"X":2,"Y":2},{"Time":137100,"X":1,"Y":0},{"Time":137227,"X":0,"Y":2},{"Time":137353,"X":0,"Y":0},{"Time":137480,"X":0,"Y":2},{"Time":137606,"X":2,"Y":0},{"Time":137733,"X":2,"Y":2},{"Time":137859,"X":2,"Y":0},{"Time":137986,"X":0,"Y":1},{"Time":138113,"X":2,"Y":2},{"Time":138239,"X":1,"Y":0},{"Time":138366,"X":1,"Y":2},{"Time":138492,"X":0,"Y":0},{"Time":138605,"X":2,"Y":0},{"Time":138654,"X":1.5,"Y":0.88},{"Time":138704,"X":1,"Y":1.5},{"Time":138754,"X":0.5,"Y":1.88},{"Time":138804,"X":0,"Y":2},{"Time":139010,"X":0,"Y":0},{"Time":139052,"X":0.5,"Y":0.120000005},{"Time":139095,"X":1,"Y":0.5},{"Time":139137,"X":1.5,"Y":1.12},{"Time":139180,"X":2,"Y":2},{"Time":139416,"X":0,"Y":2},{"Time":139458,"X":0.5,"Y":1.88},{"Time":139501,"X":1,"Y":1.5},{"Time":139543,"X":1.5,"Y":0.88},{"Time":139586,"X":2,"Y":0},{"Time":139821,"X":0,"Y":0},{"Time":139872,"X":1,"Y":0},{"Time":139923,"X":2,"Y":0},{"Time":139973,"X":2,"Y":1},{"Time":140024,"X":1,"Y":1},{"Time":140075,"X":0,"Y":1},{"Time":140125,"X":0,"Y":2},{"Time":140176,"X":1,"Y":2},{"Time":140227,"X":2,"Y":2},{"Time":140277,"X":2,"Y":1},{"Time":140328,"X":2,"Y":0},{"Time":140379,"X":1,"Y":0},{"Time":140429,"X":1,"Y":1},{"Time":140480,"X":1,"Y":2},{"Time":140531,"X":0,"Y":2},{"Time":140581,"X":0,"Y":1},{"Time":140632,"X":0,"Y":0},{"Time":140683,"X":1,"Y":0},{"Time":140733,"X":2,"Y":0},{"Time":140784,"X":2,"Y":1},{"Time":140835,"X":2,"Y":2},{"Time":140885,"X":1,"Y":2},{"Time":140936,"X":0,"Y":2},{"Time":140987,"X":0,"Y":1},{"Time":141037,"X":1,"Y":1},{"Time":141088,"X":2,"Y":1},{"Time":141139,"X":2,"Y":0},{"Time":141189,"X":1,"Y":0},{"Time":141240,"X":0,"Y":0},{"Time":141291,"X":0,"Y":1},{"Time":141341,"X":0,"Y":2},{"Time":141392,"X":1,"Y":2},{"Time":141443,"X":2,"Y":2},{"Time":141494,"X":2,"Y":1},{"Time":141544,"X":2,"Y":0},{"Time":141595,"X":1,"Y":0},{"Time":141646,"X":1,"Y":1},{"Time":141696,"X":1,"Y":2},{"Time":141747,"X":0,"Y":2},{"Time":141798,"X":0,"Y":1},{"Time":141848,"X":0,"Y":0},{"Time":141899,"X":1,"Y":0},{"Time":141950,"X":2,"Y":0},{"Time":142000,"X":2,"Y":1},{"Time":142051,"X":1,"Y":1},{"Time":142102,"X":0,"Y":1},{"Time":142152,"X":0,"Y":2},{"Time":142203,"X":1,"Y":2},{"Time":142254,"X":2,"Y":2},{"Time":142304,"X":2,"Y":1},{"Time":142355,"X":2,"Y":0},{"Time":142406,"X":1,"Y":0},{"Time":142456,"X":1,"Y":1},{"Time":142507,"X":1,"Y":2},{"Time":142558,"X":0,"Y":2},{"Time":142608,"X":0,"Y":1},{"Time":142659,"X":0,"Y":0},{"Time":142710,"X":1,"Y":0},{"Time":142760,"X":2,"Y":0},{"Time":142811,"X":2,"Y":1},{"Time":142862,"X":1,"Y":1},{"Time":142912,"X":0,"Y":1},{"Time":142963,"X":0,"Y":2},{"Time":143014,"X":1,"Y":2},{"Time":143064,"X":2,"Y":2},{"Time":143166,"X":1,"Y":0},{"Time":143267,"X":0,"Y":2},{"Time":143437,"X":2,"Y":0},{"Time":143608,"X":2,"Y":2},{"Time":143778,"X":0,"Y":0},{"Time":143949,"X":0,"Y":2},{"Time":144119,"X":2,"Y":0},{"Time":144290,"X":0,"Y":1},{"Time":144460,"X":2,"Y":1},{"Time":144631,"X":0,"Y":2},{"Time":144801,"X":2,"Y":2},{"Time":144972,"X":0,"Y":1},{"Time":145142,"X":2,"Y":0},{"Time":145312,"X":1,"Y":2},{"Time":145483,"X":0,"Y":0},{"Time":145653,"X":0,"Y":2},{"Time":145824,"X":1,"Y":0},{"Time":145994,"X":2,"Y":2},{"Time":146079,"X":0,"Y":0},{"Time":146164,"X":2,"Y":1},{"Time":146250,"X":0,"Y":1},{"Time":146335,"X":2,"Y":0},{"Time":146420,"X":0,"Y":2},{"Time":146505,"X":1,"Y":0},{"Time":146591,"X":1,"Y":2},{"Time":146676,"X":0,"Y":0},{"Time":146761,"X":2,"Y":2},{"Time":146846,"X":0,"Y":1},{"Time":146932,"X":2,"Y":1},{"Time":147017,"X":0,"Y":2},{"Time":147102,"X":2,"Y":0},{"Time":147187,"X":1,"Y":2},{"Time":147272,"X":1,"Y":0},{"Time":147358,"X":2,"Y":2},{"Time":147443,"X":0,"Y":0},{"Time":147528,"X":2,"Y":1},{"Time":147613,"X":0,"Y":2},{"Time":147699,"X":1,"Y":0},{"Time":147784,"X":2,"Y":2},{"Time":147869,"X":0,"Y":1},{"Time":147954,"X":2,"Y":0},{"Time":148039,"X":1,"Y":2},{"Time":148125,"X":0,"Y":0},{"Time":148210,"X":2,"Y":1},{"Time":148295,"X":0,"Y":1},{"Time":148380,"X":2,"Y":0},{"Time":148466,"X":0,"Y":2},{"Time":148551,"X":1,"Y":0},{"Time":148636,"X":1,"Y":2},{"Time":148721,"X":0,"Y":0},{"Time":148806,"X":0,"Y":2},{"Time":148892,"X":2,"Y":0},{"Time":148977,"X":2,"Y":2},{"Time":149062,"X":1,"Y":0},{"Time":149147,"X":0,"Y":2},{"Time":149233,"X":2,"Y":1},{"Time":149318,"X":0,"Y":0},{"Time":149403,"X":1,"Y":2},{"Time":149488,"X":2,"Y":0},{"Time":149574,"X":0,"Y":1},{"Time":149659,"X":2,"Y":1},{"Time":149744,"X":0,"Y":0},{"Time":149829,"X":2,"Y":2},{"Time":149914,"X":1,"Y":0},{"Time":150000,"X":1,"Y":2},{"Time":150085,"X":2,"Y":0},{"Time":150170,"X":2,"Y":2},{"Time":150255,"X":1,"Y":0},{"Time":150341,"X":1,"Y":2},{"Time":150426,"X":0,"Y":0},{"Time":150511,"X":0,"Y":2},{"Time":150596,"X":1,"Y":0},{"Time":150682,"X":2,"Y":2},{"Time":150767,"X":0,"Y":1},{"Time":150852,"X":2,"Y":0},{"Time":150937,"X":1,"Y":2},{"Time":151022,"X":0,"Y":0},{"Time":151108,"X":2,"Y":1},{"Time":151193,"X":0,"Y":1},{"Time":151278,"X":2,"Y":2},{"Time":151363,"X":0,"Y":2},{"Time":151449,"X":2,"Y":1},{"Time":151534,"X":0,"Y":0},{"Time":151619,"X":1,"Y":2},{"Time":151704,"X":2,"Y":0},{"Time":151789,"X":0,"Y":1},{"Time":151875,"X":2,"Y":2},{"Time":151960,"X":1,"Y":0},{"Time":152045,"X":1,"Y":2},{"Time":152130,"X":0,"Y":0},{"Time":152216,"X":0,"Y":2},{"Time":152301,"X":1,"Y":0},{"Time":152386,"X":2,"Y":2},{"Time":152471,"X":0,"Y":1},{"Time":152556,"X":2,"Y":1},{"Time":152642,"X":0,"Y":2},{"Time":152727,"X":2,"Y":2},{"Time":152812,"X":0,"Y":1},{"Time":152897,"X":2,"Y":1},{"Time":152983,"X":0,"Y":0},{"Time":153068,"X":2,"Y":0},{"Time":153153,"X":0,"Y":1},{"Time":153238,"X":2,"Y":2},{"Time":153324,"X":1,"Y":0},{"Time":153409,"X":0,"Y":2},{"Time":153494,"X":2,"Y":1},{"Time":153579,"X":0,"Y":1},{"Time":153664,"X":2,"Y":2},{"Time":153750,"X":0,"Y":0},{"Time":153835,"X":1,"Y":2},{"Time":153920,"X":1,"Y":0},{"Time":154005,"X":2,"Y":2},{"Time":154091,"X":2,"Y":0},{"Time":154176,"X":1,"Y":2},{"Time":154261,"X":1,"Y":0},{"Time":154346,"X":0,"Y":2},{"Time":154432,"X":0,"Y":0},{"Time":154517,"X":2,"Y":2},{"Time":154602,"X":2,"Y":0},{"Time":154687,"X":0,"Y":2},{"Time":154772,"X":2,"Y":1},{"Time":154858,"X":0,"Y":1},{"Time":154943,"X":2,"Y":2},{"Time":155028,"X":1,"Y":0},{"Time":155113,"X":1,"Y":2},{"Time":155199,"X":2,"Y":0},{"Time":155284,"X":0,"Y":2},{"Time":155369,"X":2,"Y":1},{"Time":155454,"X":0,"Y":1},{"Time":155539,"X":2,"Y":0},{"Time":155625,"X":0,"Y":0},{"Time":155710,"X":2,"Y":1},{"Time":155795,"X":0,"Y":2},{"Time":155880,"X":1,"Y":0},{"Time":155966,"X":2,"Y":2},{"Time":156051,"X":0,"Y":1},{"Time":156136,"X":2,"Y":0},{"Time":156221,"X":1,"Y":2},{"Time":156306,"X":1,"Y":0},{"Time":156392,"X":0,"Y":2},{"Time":156477,"X":0,"Y":0},{"Time":156562,"X":1,"Y":2},{"Time":156647,"X":1,"Y":0},{"Time":156733,"X":2,"Y":2},{"Time":156818,"X":0,"Y":1},{"Time":156903,"X":2,"Y":1},{"Time":156988,"X":0,"Y":2},{"Time":157074,"X":1,"Y":0},{"Time":157159,"X":1,"Y":2},{"Time":157244,"X":0,"Y":0},{"Time":157329,"X":0,"Y":2},{"Time":157414,"X":1,"Y":0},{"Time":157500,"X":2,"Y":2},{"Time":157585,"X":0,"Y":1},{"Time":157670,"X":2,"Y":0},{"Time":157755,"X":1,"Y":2},{"Time":157841,"X":0,"Y":0},{"Time":157926,"X":2,"Y":1},{"Time":158011,"X":0,"Y":1},{"Time":158096,"X":2,"Y":2},{"Time":158182,"X":0,"Y":2},{"Time":158267,"X":2,"Y":1},{"Time":158352,"X":0,"Y":0},{"Time":158437,"X":1,"Y":2},{"Time":158522,"X":1,"Y":0},{"Time":158608,"X":2,"Y":2},{"Time":158693,"X":2,"Y":0},{"Time":158778,"X":1,"Y":2},{"Time":158863,"X":1,"Y":0},{"Time":158949,"X":0,"Y":2},{"Time":159034,"X":0,"Y":0},{"Time":159119,"X":2,"Y":2},{"Time":159204,"X":2,"Y":0},{"Time":159289,"X":0,"Y":2},{"Time":159375,"X":2,"Y":1},{"Time":159460,"X":0,"Y":1},{"Time":159545,"X":2,"Y":2},{"Time":159630,"X":0,"Y":0},{"Time":159716,"X":1,"Y":2},{"Time":159801,"X":1,"Y":0},{"Time":159886,"X":0,"Y":2},{"Time":159971,"X":2,"Y":0},{"Time":160056,"X":0,"Y":1},{"Time":160142,"X":2,"Y":1},{"Time":160227,"X":0,"Y":0},{"Time":160312,"X":2,"Y":0},{"Time":160397,"X":0,"Y":1},{"Time":160483,"X":2,"Y":2},{"Time":160568,"X":1,"Y":0},{"Time":160653,"X":0,"Y":2},{"Time":160738,"X":2,"Y":1},{"Time":160824,"X":0,"Y":0},{"Time":160909,"X":1,"Y":2},{"Time":160994,"X":2,"Y":0},{"Time":161079,"X":0,"Y":1},{"Time":161164,"X":2,"Y":2},{"Time":161250,"X":1,"Y":0},{"Time":161335,"X":0,"Y":2},{"Time":161420,"X":2,"Y":1},{"Time":161505,"X":0,"Y":0},{"Time":161591,"X":1,"Y":2},{"Time":161676,"X":2,"Y":0},{"Time":161761,"X":0,"Y":1},{"Time":161846,"X":2,"Y":1},{"Time":161932,"X":0,"Y":0},{"Time":162017,"X":2,"Y":2},{"Time":162102,"X":1,"Y":0},{"Time":162187,"X":1,"Y":2},{"Time":162272,"X":2,"Y":0},{"Time":162358,"X":0,"Y":2},{"Time":162443,"X":2,"Y":1},{"Time":162528,"X":0,"Y":1},{"Time":162613,"X":2,"Y":2},{"Time":162699,"X":0,"Y":2},{"Time":162784,"X":2,"Y":1},{"Time":162869,"X":0,"Y":0},{"Time":162954,"X":1,"Y":2},{"Time":163039,"X":2,"Y":0},{"Time":163125,"X":0,"Y":1},{"Time":163210,"X":2,"Y":2},{"Time":163295,"X":1,"Y":0},{"Time":163380,"X":0,"Y":2},{"Time":163466,"X":0,"Y":0},{"Time":163551,"X":1,"Y":2},{"Time":163636,"X":2,"Y":0},{"Time":163721,"X":2,"Y":2},{"Time":163806,"X":1,"Y":0},{"Time":163892,"X":0,"Y":2},{"Time":163977,"X":2,"Y":1},{"Time":164062,"X":0,"Y":1},{"Time":164147,"X":2,"Y":2},{"Time":164233,"X":1,"Y":0},{"Time":164318,"X":1,"Y":2},{"Time":164403,"X":2,"Y":0},{"Time":164488,"X":0,"Y":2},{"Time":164574,"X":2,"Y":1},{"Time":164659,"X":0,"Y":1},{"Time":164744,"X":2,"Y":2},{"Time":164829,"X":0,"Y":2},{"Time":164914,"X":2,"Y":1},{"Time":165000,"X":0,"Y":1},{"Time":165085,"X":2,"Y":0},{"Time":165170,"X":0,"Y":0},{"Time":165255,"X":2,"Y":1},{"Time":165341,"X":0,"Y":2},{"Time":165426,"X":1,"Y":0},{"Time":165511,"X":2,"Y":2},{"Time":165596,"X":0,"Y":1},{"Time":165682,"X":2,"Y":0},{"Time":165767,"X":1,"Y":2},{"Time":165852,"X":0,"Y":0},{"Time":165937,"X":2,"Y":1},{"Time":166022,"X":0,"Y":2},{"Time":166108,"X":1,"Y":0},{"Time":166193,"X":1,"Y":2},{"Time":166278,"X":0,"Y":0},{"Time":166363,"X":2,"Y":2},{"Time":166449,"X":0,"Y":1},{"Time":166534,"X":2,"Y":1},{"Time":166619,"X":0,"Y":2},{"Time":166704,"X":2,"Y":2},{"Time":166789,"X":0,"Y":1},{"Time":166875,"X":2,"Y":0},{"Time":166960,"X":1,"Y":2},{"Time":167045,"X":1,"Y":0},{"Time":167130,"X":0,"Y":2},{"Time":167216,"X":0,"Y":0},{"Time":167301,"X":2,"Y":2},{"Time":167386,"X":0,"Y":1},{"Time":167471,"X":2,"Y":1},{"Time":167556,"X":0,"Y":2},{"Time":167642,"X":2,"Y":0},{"Time":167727,"X":1,"Y":2},{"Time":167812,"X":1,"Y":0},{"Time":167926,"X":1,"Y":2},{"Time":168039,"X":0,"Y":0},{"Time":168153,"X":2,"Y":1},{"Time":168267,"X":0,"Y":1},{"Time":168380,"X":2,"Y":2},{"Time":168494,"X":-0.099999905,"Y":2.1},{"Time":168608,"X":2.16,"Y":1},{"Time":168721,"X":-0.099999905,"Y":-0.099999905},{"Time":168835,"X":1,"Y":2},{"Time":168949,"X":2.22,"Y":-0.22000003},{"Time":169062,"X":-0.20000005,"Y":1},{"Time":169176,"X":2.2,"Y":2.2},{"Time":169289,"X":1,"Y":-0.099999905},{"Time":169403,"X":1,"Y":2.1},{"Time":169517,"X":-0.099999905,"Y":-0.099999905},{"Time":169630,"X":-0.21000004,"Y":2.21},{"Time":169744,"X":1,"Y":-0.32999992},{"Time":169858,"X":2.33,"Y":2.33},{"Time":169971,"X":-0.46000004,"Y":1},{"Time":170085,"X":2.69,"Y":1},{"Time":170199,"X":-0.20000005,"Y":2.2},{"Time":170312,"X":1,"Y":-0.29999995},{"Time":170426,"X":1,"Y":2.4},{"Time":170540,"X":0,"Y":0},{"Time":170625,"X":2,"Y":2},{"Time":170710,"X":0,"Y":1},{"Time":170795,"X":2,"Y":1},{"Time":170880,"X":0,"Y":2},{"Time":170966,"X":2,"Y":0},{"Time":171051,"X":1,"Y":2},{"Time":171136,"X":1,"Y":0},{"Time":171221,"X":2,"Y":2},{"Time":171306,"X":2,"Y":0},{"Time":171392,"X":1,"Y":2},{"Time":171477,"X":1,"Y":0},{"Time":171562,"X":0,"Y":2},{"Time":171647,"X":0,"Y":0},{"Time":171733,"X":1,"Y":2},{"Time":171818,"X":2,"Y":0},{"Time":171903,"X":0,"Y":1},{"Time":171988,"X":2,"Y":2},{"Time":172074,"X":1,"Y":0},{"Time":172159,"X":0,"Y":2},{"Time":172244,"X":2,"Y":1},{"Time":172329,"X":0,"Y":1},{"Time":172414,"X":2,"Y":2},{"Time":172500,"X":0,"Y":0},{"Time":172585,"X":1,"Y":2},{"Time":172670,"X":1,"Y":0},{"Time":172755,"X":0,"Y":2},{"Time":172841,"X":2,"Y":0},{"Time":172926,"X":0,"Y":1},{"Time":173011,"X":2,"Y":2},{"Time":173096,"X":1,"Y":0},{"Time":173182,"X":0,"Y":2},{"Time":173267,"X":2,"Y":1},{"Time":173437,"X":0,"Y":1},{"Time":173608,"X":2,"Y":1},{"Time":173778,"X":0,"Y":1},{"Time":173949,"X":2,"Y":1},{"Time":174119,"X":0,"Y":2},{"Time":174289,"X":2,"Y":2.25},{"Time":174460,"X":0,"Y":2.25},{"Time":174630,"X":2,"Y":2.33},{"Time":174801,"X":0,"Y":2.5},{"Time":174971,"X":2,"Y":2.5},{"Time":175142,"X":0,"Y":2.67},{"Time":175312,"X":2.1,"Y":2.1},{"Time":175397,"X":-0.099999905,"Y":-0.099999905},{"Time":175483,"X":2.1,"Y":2.1},{"Time":175568,"X":-0.099999905,"Y":-0.099999905},{"Time":175653,"X":1,"Y":2},{"Time":175738,"X":1,"Y":0},{"Time":175824,"X":1,"Y":1.9},{"Time":175909,"X":1,"Y":0.100000024},{"Time":175994,"X":0.100000024,"Y":1.9},{"Time":176164,"X":2,"Y":0},{"Time":176335,"X":2,"Y":2},{"Time":176356,"X":1.92,"Y":1.5},{"Time":176377,"X":1.7,"Y":1.04},{"Time":176399,"X":1.38,"Y":0.62},{"Time":176420,"X":0.96000004,"Y":0.29999995},{"Time":176441,"X":0.5,"Y":0.08000004},{"Time":176463,"X":0,"Y":0},{"Time":176505,"X":0,"Y":2},{"Time":176526,"X":0.5,"Y":2},{"Time":176547,"X":0.96000004,"Y":1.96},{"Time":176569,"X":1.38,"Y":1.88},{"Time":176590,"X":1.7,"Y":1.7},{"Time":176611,"X":1.92,"Y":1.4200001},{"Time":176633,"X":2,"Y":1},{"Time":176676,"X":0,"Y":0},{"Time":176718,"X":0,"Y":1},{"Time":176761,"X":0,"Y":2},{"Time":176846,"X":2,"Y":0},{"Time":176889,"X":2,"Y":1},{"Time":176932,"X":2,"Y":2},{"Time":177017,"X":0,"Y":0},{"Time":177038,"X":0.5,"Y":0},{"Time":177059,"X":0.96000004,"Y":0.03999996},{"Time":177081,"X":1.38,"Y":0.120000005},{"Time":177102,"X":1.7,"Y":0.29999995},{"Time":177123,"X":1.92,"Y":0.58000004},{"Time":177145,"X":2,"Y":1},{"Time":177187,"X":0,"Y":2},{"Time":177208,"X":0,"Y":1.5},{"Time":177229,"X":0.03999996,"Y":1.04},{"Time":177251,"X":0.120000005,"Y":0.62},{"Time":177272,"X":0.29999995,"Y":0.29999995},{"Time":177293,"X":0.58000004,"Y":0.08000004},{"Time":177315,"X":1,"Y":0},{"Time":177358,"X":2,"Y":2},{"Time":177400,"X":1,"Y":2},{"Time":177443,"X":0,"Y":2},{"Time":177528,"X":2,"Y":0},{"Time":177571,"X":1,"Y":0},{"Time":177613,"X":0,"Y":0},{"Time":177699,"X":2,"Y":2},{"Time":177720,"X":1.5,"Y":1.92},{"Time":177741,"X":1.02,"Y":1.7},{"Time":177762,"X":0.55999994,"Y":1.36},{"Time":177783,"X":0.14999998,"Y":0.92999995},{"Time":177804,"X":-0.21000004,"Y":0.41999996},{"Time":177826,"X":-0.5,"Y":-0.119999886},{"Time":177869,"X":2,"Y":0},{"Time":177890,"X":1.92,"Y":0.5},{"Time":177911,"X":1.7,"Y":0.98},{"Time":177933,"X":1.36,"Y":1.44},{"Time":177954,"X":0.92999995,"Y":1.85},{"Time":177975,"X":0.41999996,"Y":2.21},{"Time":177997,"X":-0.119999886,"Y":2.5},{"Time":178039,"X":0,"Y":0},{"Time":178082,"X":1,"Y":0},{"Time":178125,"X":2,"Y":0},{"Time":178210,"X":0,"Y":2},{"Time":178253,"X":1,"Y":2},{"Time":178295,"X":2,"Y":2},{"Time":178380,"X":2,"Y":0},{"Time":178401,"X":2,"Y":0.5},{"Time":178422,"X":1.96,"Y":0.96000004},{"Time":178444,"X":1.88,"Y":1.38},{"Time":178465,"X":1.7,"Y":1.7},{"Time":178486,"X":1.4200001,"Y":1.92},{"Time":178508,"X":1,"Y":2},{"Time":178551,"X":1,"Y":0},{"Time":178572,"X":0.58000004,"Y":0.08000004},{"Time":178593,"X":0.29999995,"Y":0.29999995},{"Time":178615,"X":0.120000005,"Y":0.62},{"Time":178636,"X":0.03999996,"Y":1.04},{"Time":178657,"X":0,"Y":1.5},{"Time":178679,"X":0,"Y":2},{"Time":178721,"X":2,"Y":2},{"Time":178764,"X":2,"Y":1},{"Time":178806,"X":2,"Y":0},{"Time":178892,"X":0,"Y":2},{"Time":178934,"X":0,"Y":1},{"Time":178977,"X":0,"Y":0},{"Time":179062,"X":2.5,"Y":2.5},{"Time":179083,"X":2.25,"Y":1.78},{"Time":179104,"X":1.9,"Y":1.15},{"Time":179126,"X":1.47,"Y":0.62},{"Time":179147,"X":0.97,"Y":0.22000003},{"Time":179168,"X":0.42999995,"Y":-0.029999971},{"Time":179190,"X":-0.119999886,"Y":-0.119999886},{"Time":179233,"X":-0.5,"Y":2.5},{"Time":179254,"X":0.21000004,"Y":2.21},{"Time":179275,"X":0.80999994,"Y":1.85},{"Time":179296,"X":1.31,"Y":1.44},{"Time":179317,"X":1.69,"Y":0.98},{"Time":179338,"X":1.92,"Y":0.5},{"Time":179360,"X":2,"Y":0},{"Time":179403,"X":0,"Y":0},{"Time":179446,"X":0,"Y":1},{"Time":179488,"X":0,"Y":2},{"Time":179574,"X":2,"Y":0},{"Time":179616,"X":2,"Y":1},{"Time":179659,"X":2,"Y":2},{"Time":179744,"X":0,"Y":0},{"Time":179765,"X":0,"Y":0.5},{"Time":179786,"X":0.03999996,"Y":0.96000004},{"Time":179808,"X":0.120000005,"Y":1.38},{"Time":179829,"X":0.29999995,"Y":1.7},{"Time":179850,"X":0.58000004,"Y":1.92},{"Time":179872,"X":1,"Y":2},{"Time":179914,"X":1,"Y":0},{"Time":179935,"X":1.4200001,"Y":0.08000004},{"Time":179956,"X":1.7,"Y":0.29999995},{"Time":179978,"X":1.88,"Y":0.62},{"Time":179999,"X":1.96,"Y":1.04},{"Time":180020,"X":2,"Y":1.5},{"Time":180042,"X":2,"Y":2},{"Time":180085,"X":0,"Y":2},{"Time":180128,"X":0,"Y":1},{"Time":180170,"X":0,"Y":0},{"Time":180255,"X":2,"Y":2},{"Time":180298,"X":2,"Y":1},{"Time":180341,"X":2,"Y":0},{"Time":180426,"X":0,"Y":0},{"Time":180447,"X":0.08000004,"Y":0.5},{"Time":180468,"X":0.29999995,"Y":0.96000004},{"Time":180490,"X":0.62,"Y":1.38},{"Time":180511,"X":1.04,"Y":1.7},{"Time":180532,"X":1.5,"Y":1.92},{"Time":180554,"X":2,"Y":2},{"Time":180596,"X":2,"Y":0},{"Time":180617,"X":1.5,"Y":0.08000004},{"Time":180638,"X":1.04,"Y":0.29999995},{"Time":180660,"X":0.62,"Y":0.62},{"Time":180681,"X":0.29999995,"Y":1.04},{"Time":180702,"X":0.08000004,"Y":1.5},{"Time":180724,"X":0,"Y":2},{"Time":180767,"X":2,"Y":2},{"Time":180809,"X":2,"Y":1},{"Time":180852,"X":2,"Y":0},{"Time":180937,"X":0,"Y":2},{"Time":180980,"X":0,"Y":1},{"Time":181022,"X":0,"Y":0},{"Time":181108,"X":2,"Y":2},{"Time":181129,"X":1.5699999,"Y":1.5},{"Time":181150,"X":1.26,"Y":1.04},{"Time":181171,"X":1,"Y":0.62},{"Time":181192,"X":0.74,"Y":0.29999995},{"Time":181213,"X":0.42999995,"Y":0.08000004},{"Time":181235,"X":0,"Y":0},{"Time":181278,"X":0,"Y":2},{"Time":181299,"X":0.5,"Y":1.5699999},{"Time":181320,"X":0.96000004,"Y":1.26},{"Time":181342,"X":1.38,"Y":1},{"Time":181363,"X":1.7,"Y":0.74},{"Time":181384,"X":1.92,"Y":0.42999995},{"Time":181406,"X":2,"Y":0},{"Time":181449,"X":0,"Y":0},{"Time":181491,"X":0,"Y":1},{"Time":181534,"X":0,"Y":2},{"Time":181619,"X":2,"Y":0},{"Time":181704,"X":1,"Y":2},{"Time":181789,"X":-0.1500001,"Y":-0.1500001},{"Time":181810,"X":-0.1400001,"Y":0.41999996},{"Time":181831,"X":-0.109999895,"Y":0.96000004},{"Time":181853,"X":-0.00999999,"Y":1.4300001},{"Time":181874,"X":0.19000006,"Y":1.81},{"Time":181895,"X":0.52,"Y":2.06},{"Time":181917,"X":1,"Y":2.15},{"Time":181960,"X":1,"Y":-0.1500001},{"Time":181981,"X":1.48,"Y":-0.059999943},{"Time":182002,"X":1.81,"Y":0.19000006},{"Time":182024,"X":2.01,"Y":0.57000005},{"Time":182045,"X":2.11,"Y":1.04},{"Time":182066,"X":2.14,"Y":1.58},{"Time":182088,"X":2.15,"Y":2.15},{"Time":182130,"X":0,"Y":2},{"Time":182173,"X":0,"Y":1},{"Time":182216,"X":0,"Y":0},{"Time":182301,"X":2,"Y":2},{"Time":182343,"X":2,"Y":1},{"Time":182386,"X":2,"Y":0},{"Time":182471,"X":-0.07999992,"Y":1.91},{"Time":182492,"X":-0.03999996,"Y":1.4200001},{"Time":182513,"X":0.03999996,"Y":0.95000005},{"Time":182535,"X":0.15999997,"Y":0.54999995},{"Time":182556,"X":0.36,"Y":0.24000001},{"Time":182577,"X":0.65999997,"Y":0.049999952},{"Time":182599,"X":1.0899999,"Y":0},{"Time":182642,"X":1.91,"Y":2.08},{"Time":182663,"X":1.4200001,"Y":2.04},{"Time":182684,"X":0.95000005,"Y":1.96},{"Time":182706,"X":0.54999995,"Y":1.84},{"Time":182727,"X":0.24000001,"Y":1.64},{"Time":182748,"X":0.049999952,"Y":1.3399999},{"Time":182770,"X":0,"Y":0.90999997},{"Time":182812,"X":2,"Y":0},{"Time":182855,"X":2,"Y":1},{"Time":182897,"X":2,"Y":2},{"Time":182983,"X":0,"Y":0},{"Time":183025,"X":0,"Y":1},{"Time":183068,"X":0,"Y":2},{"Time":183153,"X":2,"Y":0},{"Time":183174,"X":1.92,"Y":0.5},{"Time":183195,"X":1.7,"Y":0.96000004},{"Time":183217,"X":1.38,"Y":1.38},{"Time":183238,"X":0.96000004,"Y":1.7},{"Time":183259,"X":0.5,"Y":1.92},{"Time":183281,"X":0,"Y":2},{"Time":183324,"X":0,"Y":0},{"Time":183345,"X":0.5,"Y":0.08000004},{"Time":183366,"X":0.96000004,"Y":0.29999995},{"Time":183387,"X":1.38,"Y":0.62},{"Time":183408,"X":1.7,"Y":1.04},{"Time":183429,"X":1.92,"Y":1.5},{"Time":183451,"X":2,"Y":2},{"Time":183494,"X":0,"Y":2},{"Time":183537,"X":0,"Y":1},{"Time":183579,"X":0,"Y":0},{"Time":183664,"X":2,"Y":2},{"Time":183707,"X":2,"Y":1},{"Time":183750,"X":2,"Y":0},{"Time":183835,"X":0,"Y":2},{"Time":183856,"X":0.08000004,"Y":1.5},{"Time":183877,"X":0.29999995,"Y":1.04},{"Time":183899,"X":0.62,"Y":0.62},{"Time":183920,"X":1.04,"Y":0.29999995},{"Time":183941,"X":1.5,"Y":0.08000004},{"Time":183963,"X":2,"Y":0},{"Time":184005,"X":2,"Y":2},{"Time":184026,"X":1.5,"Y":1.92},{"Time":184047,"X":1.04,"Y":1.7},{"Time":184069,"X":0.62,"Y":1.38},{"Time":184090,"X":0.29999995,"Y":0.96000004},{"Time":184111,"X":0.08000004,"Y":0.5},{"Time":184133,"X":0,"Y":0},{"Time":184176,"X":2,"Y":0},{"Time":184218,"X":2,"Y":1},{"Time":184261,"X":2,"Y":2},{"Time":184346,"X":0,"Y":0},{"Time":184389,"X":0,"Y":1},{"Time":184432,"X":0,"Y":2},{"Time":184517,"X":2.12,"Y":-0.119999886},{"Time":184538,"X":1.88,"Y":0.82000005},{"Time":184559,"X":1.53,"Y":1.46},{"Time":184581,"X":1.0899999,"Y":1.84},{"Time":184602,"X":0.6,"Y":2.04},{"Time":184623,"X":0.059999943,"Y":2.11},{"Time":184645,"X":-0.5,"Y":2.12},{"Time":184687,"X":-0.119999886,"Y":-0.5},{"Time":184708,"X":0.82000005,"Y":-0.25},{"Time":184729,"X":1.46,"Y":0.100000024},{"Time":184751,"X":1.84,"Y":0.53},{"Time":184772,"X":2.04,"Y":1.03},{"Time":184793,"X":2.11,"Y":1.5699999},{"Time":184815,"X":2.12,"Y":2.12},{"Time":184858,"X":0,"Y":2},{"Time":184900,"X":0,"Y":1},{"Time":184943,"X":0,"Y":0},{"Time":185028,"X":2,"Y":2},{"Time":185071,"X":2,"Y":1},{"Time":185113,"X":2,"Y":0},{"Time":185199,"X":0,"Y":2},{"Time":185220,"X":0.08000004,"Y":1.5},{"Time":185241,"X":0.29999995,"Y":1.04},{"Time":185262,"X":0.62,"Y":0.62},{"Time":185283,"X":1.04,"Y":0.29999995},{"Time":185304,"X":1.5,"Y":0.08000004},{"Time":185326,"X":2,"Y":0},{"Time":185369,"X":2,"Y":2},{"Time":185390,"X":1.5,"Y":1.92},{"Time":185411,"X":1.04,"Y":1.7},{"Time":185433,"X":0.62,"Y":1.38},{"Time":185454,"X":0.29999995,"Y":0.96000004},{"Time":185475,"X":0.08000004,"Y":0.5},{"Time":185497,"X":0,"Y":0},{"Time":185539,"X":2,"Y":0},{"Time":185582,"X":2,"Y":1},{"Time":185625,"X":2,"Y":2},{"Time":185710,"X":0,"Y":0},{"Time":185753,"X":0,"Y":1},{"Time":185795,"X":0,"Y":2},{"Time":185880,"X":2,"Y":0},{"Time":185901,"X":2,"Y":0.5},{"Time":185922,"X":1.96,"Y":0.96000004},{"Time":185944,"X":1.88,"Y":1.38},{"Time":185965,"X":1.7,"Y":1.7},{"Time":185986,"X":1.4200001,"Y":1.92},{"Time":186008,"X":1,"Y":2},{"Time":186051,"X":1,"Y":0},{"Time":186072,"X":0.58000004,"Y":0.08000004},{"Time":186093,"X":0.29999995,"Y":0.29999995},{"Time":186115,"X":0.120000005,"Y":0.62},{"Time":186136,"X":0.03999996,"Y":1.04},{"Time":186157,"X":0,"Y":1.5},{"Time":186179,"X":0,"Y":2},{"Time":186221,"X":2,"Y":2},{"Time":186264,"X":2,"Y":1},{"Time":186306,"X":2,"Y":0},{"Time":186392,"X":0,"Y":2},{"Time":186434,"X":0,"Y":1},{"Time":186477,"X":0,"Y":0},{"Time":186562,"X":2,"Y":2},{"Time":186583,"X":2,"Y":1.5},{"Time":186604,"X":1.96,"Y":1.04},{"Time":186626,"X":1.88,"Y":0.62},{"Time":186647,"X":1.7,"Y":0.29999995},{"Time":186668,"X":1.4200001,"Y":0.08000004},{"Time":186690,"X":1,"Y":0},{"Time":186733,"X":0,"Y":2},{"Time":186754,"X":0.5,"Y":2},{"Time":186775,"X":0.96000004,"Y":1.96},{"Time":186796,"X":1.38,"Y":1.88},{"Time":186817,"X":1.7,"Y":1.7},{"Time":186838,"X":1.92,"Y":1.4200001},{"Time":186860,"X":2,"Y":1},{"Time":186903,"X":0,"Y":0},{"Time":186946,"X":0,"Y":1},{"Time":186988,"X":0,"Y":2},{"Time":187031,"X":1,"Y":2},{"Time":187074,"X":1,"Y":1},{"Time":187116,"X":1,"Y":0},{"Time":187159,"X":2,"Y":0},{"Time":187201,"X":2,"Y":1},{"Time":187244,"X":2,"Y":2},{"Time":187287,"X":1,"Y":2},{"Time":187329,"X":0,"Y":2},{"Time":187372,"X":0,"Y":1},{"Time":187414,"X":1,"Y":1},{"Time":187457,"X":2,"Y":1},{"Time":187500,"X":2,"Y":0},{"Time":187542,"X":1,"Y":0},{"Time":187585,"X":0,"Y":0},{"Time":187628,"X":0,"Y":1},{"Time":187670,"X":0,"Y":2},{"Time":187713,"X":1,"Y":2},{"Time":187755,"X":2,"Y":2},{"Time":187798,"X":2,"Y":1},{"Time":187841,"X":2,"Y":0},{"Time":187883,"X":1,"Y":0},{"Time":187926,"X":1,"Y":1},{"Time":187968,"X":1,"Y":2},{"Time":188011,"X":0,"Y":2},{"Time":188054,"X":0,"Y":1},{"Time":188096,"X":0,"Y":0},{"Time":188139,"X":1,"Y":0},{"Time":188182,"X":2,"Y":0},{"Time":188224,"X":2,"Y":1},{"Time":188267,"X":0,"Y":2},{"Time":188309,"X":0,"Y":1},{"Time":188352,"X":0,"Y":0},{"Time":188395,"X":1,"Y":0},{"Time":188437,"X":1,"Y":1},{"Time":188480,"X":1,"Y":2},{"Time":188522,"X":2,"Y":2},{"Time":188565,"X":2,"Y":1},{"Time":188608,"X":2,"Y":0},{"Time":188650,"X":1,"Y":0},{"Time":188693,"X":0,"Y":0},{"Time":188735,"X":0,"Y":1},{"Time":188778,"X":0,"Y":2},{"Time":188821,"X":1,"Y":2},{"Time":188863,"X":2,"Y":2},{"Time":188906,"X":2,"Y":1},{"Time":188949,"X":1,"Y":1},{"Time":188991,"X":0,"Y":1},{"Time":189034,"X":0,"Y":0},{"Time":189076,"X":1,"Y":0},{"Time":189119,"X":2,"Y":0},{"Time":189162,"X":2,"Y":1},{"Time":189204,"X":2,"Y":2},{"Time":189247,"X":1,"Y":2},{"Time":189289,"X":0,"Y":2},{"Time":189332,"X":0,"Y":1},{"Time":189375,"X":1,"Y":1},{"Time":189417,"X":2,"Y":1},{"Time":189460,"X":2,"Y":0},{"Time":189503,"X":1,"Y":0},{"Time":189545,"X":0,"Y":0},{"Time":189588,"X":0,"Y":1},{"Time":189630,"X":2,"Y":2},{"Time":189673,"X":2,"Y":1},{"Time":189716,"X":2,"Y":0},{"Time":189758,"X":1,"Y":0},{"Time":189801,"X":1,"Y":1},{"Time":189843,"X":1,"Y":2},{"Time":189886,"X":0,"Y":2},{"Time":189929,"X":0,"Y":1},{"Time":189971,"X":0,"Y":0},{"Time":190014,"X":1,"Y":0},{"Time":190056,"X":2,"Y":0},{"Time":190099,"X":2,"Y":1},{"Time":190142,"X":2,"Y":2},{"Time":190184,"X":1,"Y":2},{"Time":190227,"X":0,"Y":2},{"Time":190270,"X":0,"Y":1},{"Time":190312,"X":1,"Y":1},{"Time":190355,"X":2,"Y":1},{"Time":190397,"X":2,"Y":0},{"Time":190440,"X":1,"Y":0},{"Time":190483,"X":0,"Y":0},{"Time":190525,"X":0,"Y":1},{"Time":190568,"X":0,"Y":2},{"Time":190610,"X":1,"Y":2},{"Time":190653,"X":2,"Y":2},{"Time":190696,"X":2,"Y":1},{"Time":190738,"X":2,"Y":0},{"Time":190781,"X":1,"Y":0},{"Time":190824,"X":0,"Y":0},{"Time":190866,"X":0,"Y":1},{"Time":190909,"X":1,"Y":1},{"Time":190951,"X":2,"Y":1},{"Time":190994,"X":2,"Y":2},{"Time":191037,"X":1,"Y":2},{"Time":191079,"X":0,"Y":2},{"Time":191122,"X":0,"Y":1},{"Time":191164,"X":0,"Y":0},{"Time":191207,"X":1,"Y":0},{"Time":191250,"X":1,"Y":1},{"Time":191292,"X":1,"Y":2},{"Time":191335,"X":2,"Y":2},{"Time":191378,"X":2,"Y":1},{"Time":191420,"X":2,"Y":0},{"Time":191463,"X":1,"Y":0},{"Time":191505,"X":0,"Y":0},{"Time":191548,"X":0,"Y":1},{"Time":191591,"X":0,"Y":2},{"Time":191633,"X":1,"Y":2},{"Time":191676,"X":2,"Y":2},{"Time":191718,"X":2,"Y":1},{"Time":191761,"X":2,"Y":0},{"Time":191804,"X":1,"Y":0},{"Time":191846,"X":1,"Y":1},{"Time":191889,"X":1,"Y":2},{"Time":191932,"X":0,"Y":2},{"Time":191974,"X":0,"Y":1},{"Time":192017,"X":0,"Y":0},{"Time":192059,"X":1,"Y":0},{"Time":192102,"X":2,"Y":0},{"Time":192145,"X":2,"Y":1},{"Time":192187,"X":2,"Y":2},{"Time":192230,"X":1,"Y":2},{"Time":192272,"X":0,"Y":2},{"Time":192315,"X":0,"Y":1},{"Time":192358,"X":2,"Y":0},{"Time":192400,"X":2,"Y":1},{"Time":192443,"X":2,"Y":2},{"Time":192485,"X":1,"Y":2},{"Time":192528,"X":0,"Y":2},{"Time":192571,"X":0,"Y":1},{"Time":192613,"X":1,"Y":1},{"Time":192656,"X":2,"Y":1},{"Time":192699,"X":2,"Y":0},{"Time":192741,"X":1,"Y":0},{"Time":192784,"X":0,"Y":0},{"Time":192826,"X":0,"Y":1},{"Time":192869,"X":0,"Y":2},{"Time":192912,"X":1,"Y":2},{"Time":192954,"X":2,"Y":2},{"Time":192997,"X":2,"Y":1},{"Time":193039,"X":2,"Y":0},{"Time":193082,"X":1,"Y":0},{"Time":193125,"X":1,"Y":1},{"Time":193167,"X":1,"Y":2},{"Time":193210,"X":0,"Y":2},{"Time":193253,"X":0,"Y":1},{"Time":193295,"X":0,"Y":0},{"Time":193338,"X":1,"Y":0},{"Time":193380,"X":2,"Y":0},{"Time":193423,"X":2,"Y":1},{"Time":193466,"X":1,"Y":1},{"Time":193508,"X":0,"Y":1},{"Time":193551,"X":0,"Y":2},{"Time":193593,"X":1,"Y":2},{"Time":193636,"X":2,"Y":2},{"Time":193679,"X":2,"Y":1},{"Time":193721,"X":0,"Y":0},{"Time":193764,"X":0,"Y":1},{"Time":193806,"X":0,"Y":2},{"Time":193849,"X":1,"Y":2},{"Time":193892,"X":1,"Y":1},{"Time":193934,"X":1,"Y":0},{"Time":193977,"X":2,"Y":0},{"Time":194020,"X":2,"Y":1},{"Time":194062,"X":2,"Y":2},{"Time":194105,"X":1,"Y":2},{"Time":194147,"X":0,"Y":2},{"Time":194190,"X":0,"Y":1},{"Time":194233,"X":1,"Y":1},{"Time":194275,"X":2,"Y":1},{"Time":194318,"X":2,"Y":0},{"Time":194360,"X":1,"Y":0},{"Time":194403,"X":0,"Y":2},{"Time":194446,"X":1,"Y":2},{"Time":194488,"X":2,"Y":2},{"Time":194531,"X":2,"Y":1},{"Time":194574,"X":2,"Y":0},{"Time":194616,"X":1,"Y":0},{"Time":194659,"X":1,"Y":1},{"Time":194701,"X":1,"Y":2},{"Time":194744,"X":0,"Y":2},{"Time":194787,"X":0,"Y":1},{"Time":194829,"X":0,"Y":0},{"Time":194872,"X":1,"Y":0},{"Time":194914,"X":2,"Y":0},{"Time":194957,"X":2,"Y":1},{"Time":195000,"X":2,"Y":2},{"Time":195042,"X":1,"Y":2},{"Time":195085,"X":0,"Y":0},{"Time":195128,"X":1,"Y":0},{"Time":195170,"X":2,"Y":0},{"Time":195213,"X":2,"Y":1},{"Time":195255,"X":1,"Y":1},{"Time":195298,"X":0,"Y":1},{"Time":195341,"X":0,"Y":2},{"Time":195383,"X":1,"Y":2},{"Time":195426,"X":2,"Y":2},{"Time":195468,"X":2,"Y":1},{"Time":195511,"X":2,"Y":0},{"Time":195554,"X":1,"Y":0},{"Time":195596,"X":1,"Y":1},{"Time":195639,"X":1,"Y":2},{"Time":195682,"X":0,"Y":2},{"Time":195724,"X":0,"Y":1},{"Time":195767,"X":0,"Y":0},{"Time":195809,"X":1,"Y":0},{"Time":195852,"X":2,"Y":0},{"Time":195895,"X":2,"Y":1},{"Time":195937,"X":2,"Y":2},{"Time":195980,"X":1,"Y":2},{"Time":196022,"X":0,"Y":2},{"Time":196065,"X":0,"Y":1},{"Time":196108,"X":1,"Y":1},{"Time":196150,"X":2,"Y":1},{"Time":196193,"X":2,"Y":0},{"Time":196235,"X":1,"Y":0},{"Time":196278,"X":0,"Y":0},{"Time":196321,"X":0,"Y":1},{"Time":196363,"X":0,"Y":2},{"Time":196406,"X":1,"Y":2},{"Time":196449,"X":2,"Y":0},{"Time":196491,"X":1,"Y":0},{"Time":196534,"X":0,"Y":0},{"Time":196577,"X":0,"Y":1},{"Time":196619,"X":1,"Y":1},{"Time":196662,"X":2,"Y":1},{"Time":196704,"X":2,"Y":2},{"Time":196747,"X":1,"Y":2},{"Time":196790,"X":0,"Y":2},{"Time":196832,"X":0,"Y":1},{"Time":196875,"X":0,"Y":0},{"Time":196918,"X":1,"Y":0},{"Time":196960,"X":1,"Y":1},{"Time":197003,"X":1,"Y":2},{"Time":197045,"X":2,"Y":2},{"Time":197088,"X":2,"Y":1},{"Time":197131,"X":2,"Y":0},{"Time":197173,"X":1,"Y":0},{"Time":197216,"X":0,"Y":0},{"Time":197258,"X":0,"Y":1},{"Time":197301,"X":1,"Y":1},{"Time":197344,"X":2,"Y":1},{"Time":197386,"X":2,"Y":2},{"Time":197429,"X":1,"Y":2},{"Time":197472,"X":0,"Y":2},{"Time":197514,"X":0,"Y":1},{"Time":197557,"X":0,"Y":0},{"Time":197599,"X":1,"Y":0},{"Time":197642,"X":1,"Y":1},{"Time":197685,"X":1,"Y":2},{"Time":197727,"X":2,"Y":2},{"Time":197770,"X":2,"Y":1},{"Time":197812,"X":2,"Y":0},{"Time":197897,"X":0,"Y":1},{"Time":197983,"X":2,"Y":2},{"Time":198068,"X":1,"Y":0},{"Time":198153,"X":0,"Y":2},{"Time":198238,"X":2,"Y":1},{"Time":198324,"X":0,"Y":0},{"Time":198409,"X":1,"Y":2},{"Time":198494,"X":2,"Y":0},{"Time":198579,"X":0,"Y":1},{"Time":198664,"X":2,"Y":1},{"Time":198750,"X":0,"Y":0},{"Time":198835,"X":1,"Y":2},{"Time":198920,"X":1,"Y":0},{"Time":199005,"X":0,"Y":2},{"Time":199091,"X":2,"Y":0},{"Time":199176,"X":0,"Y":1},{"Time":199261,"X":2,"Y":1},{"Time":199346,"X":0,"Y":0},{"Time":199432,"X":2,"Y":0},{"Time":199517,"X":0,"Y":1},{"Time":199602,"X":2,"Y":2},{"Time":199687,"X":1,"Y":0},{"Time":199772,"X":0,"Y":2},{"Time":199858,"X":2,"Y":1},{"Time":199943,"X":0,"Y":1},{"Time":200028,"X":2,"Y":2},{"Time":200113,"X":0,"Y":0},{"Time":200199,"X":1,"Y":2},{"Time":200284,"X":1,"Y":0},{"Time":200369,"X":0,"Y":2},{"Time":200454,"X":0,"Y":0},{"Time":200539,"X":1,"Y":2},{"Time":200625,"X":1,"Y":0},{"Time":200710,"X":2,"Y":2},{"Time":200795,"X":2,"Y":0},{"Time":200880,"X":1,"Y":2},{"Time":200966,"X":0,"Y":0},{"Time":201051,"X":2,"Y":1},{"Time":201136,"X":0,"Y":2},{"Time":201221,"X":1,"Y":0},{"Time":201306,"X":2,"Y":2},{"Time":201392,"X":0,"Y":1},{"Time":201477,"X":2,"Y":0},{"Time":201562,"X":1,"Y":2},{"Time":201647,"X":0,"Y":0},{"Time":201733,"X":2,"Y":1},{"Time":201818,"X":0,"Y":2},{"Time":201903,"X":1,"Y":0},{"Time":201988,"X":1,"Y":2},{"Time":202074,"X":2,"Y":0},{"Time":202159,"X":2,"Y":2},{"Time":202244,"X":1,"Y":0},{"Time":202329,"X":0,"Y":2},{"Time":202414,"X":2,"Y":1},{"Time":202500,"X":0,"Y":1},{"Time":202585,"X":2,"Y":2},{"Time":202670,"X":0,"Y":0},{"Time":202755,"X":1,"Y":2},{"Time":202841,"X":1,"Y":0},{"Time":202926,"X":0,"Y":2},{"Time":203011,"X":2,"Y":0},{"Time":203096,"X":0,"Y":1},{"Time":203182,"X":2,"Y":1},{"Time":203267,"X":0,"Y":0},{"Time":203352,"X":2,"Y":0},{"Time":203437,"X":0,"Y":1},{"Time":203522,"X":2,"Y":2},{"Time":203608,"X":1,"Y":0},{"Time":203693,"X":0,"Y":2},{"Time":203778,"X":2,"Y":1},{"Time":203863,"X":0,"Y":0},{"Time":203949,"X":1,"Y":2},{"Time":204034,"X":2,"Y":0},{"Time":204119,"X":0,"Y":1},{"Time":204204,"X":2,"Y":2},{"Time":204289,"X":1,"Y":0},{"Time":204375,"X":1,"Y":2},{"Time":204460,"X":0,"Y":0},{"Time":204545,"X":0,"Y":2},{"Time":204630,"X":1,"Y":0},{"Time":204716,"X":2,"Y":2},{"Time":204801,"X":0,"Y":1},{"Time":204886,"X":2,"Y":0},{"Time":204971,"X":1,"Y":2},{"Time":205056,"X":0,"Y":0},{"Time":205142,"X":2,"Y":1},{"Time":205227,"X":0,"Y":1},{"Time":205312,"X":2,"Y":0},{"Time":205397,"X":0,"Y":2},{"Time":205483,"X":1,"Y":0},{"Time":205568,"X":1,"Y":2},{"Time":205653,"X":0,"Y":0},{"Time":205738,"X":2,"Y":2},{"Time":205824,"X":0,"Y":1},{"Time":205909,"X":2,"Y":1},{"Time":205994,"X":0,"Y":2},{"Time":206079,"X":2,"Y":2},{"Time":206164,"X":0,"Y":1},{"Time":206250,"X":2,"Y":0},{"Time":206335,"X":1,"Y":2},{"Time":206420,"X":0,"Y":0},{"Time":206505,"X":2,"Y":1},{"Time":206591,"X":0,"Y":2},{"Time":206676,"X":1,"Y":0},{"Time":206761,"X":1,"Y":2},{"Time":206846,"X":2,"Y":0},{"Time":206932,"X":2,"Y":2},{"Time":207017,"X":1,"Y":0},{"Time":207102,"X":0,"Y":2},{"Time":207187,"X":2,"Y":1},{"Time":207272,"X":0,"Y":1},{"Time":207358,"X":2,"Y":0},{"Time":207443,"X":0,"Y":2},{"Time":207528,"X":1,"Y":0},{"Time":207613,"X":1,"Y":2},{"Time":207699,"X":0,"Y":0},{"Time":207784,"X":0,"Y":2},{"Time":207869,"X":1,"Y":0},{"Time":207954,"X":2,"Y":2},{"Time":208039,"X":0,"Y":1},{"Time":208125,"X":2,"Y":0},{"Time":208210,"X":1,"Y":2},{"Time":208295,"X":0,"Y":0},{"Time":208380,"X":2,"Y":1},{"Time":208466,"X":0,"Y":1},{"Time":208551,"X":2,"Y":2},{"Time":208636,"X":0,"Y":2},{"Time":208721,"X":2,"Y":1},{"Time":208806,"X":0,"Y":1},{"Time":208892,"X":2,"Y":0},{"Time":208977,"X":0,"Y":0},{"Time":209062,"X":2,"Y":1},{"Time":209233,"X":0,"Y":2},{"Time":209403,"X":2,"Y":1},{"Time":209403,"X":2.17,"Y":1},{"Time":209574,"X":0,"Y":1},{"Time":209744,"X":2,"Y":0},{"Time":209914,"X":1,"Y":2},{"Time":210085,"X":1,"Y":0},{"Time":210170,"X":1,"Y":2},{"Time":210255,"X":1,"Y":0},{"Time":210341,"X":1,"Y":2},{"Time":210426,"X":0,"Y":0},{"Time":210596,"X":2,"Y":2},{"Time":210767,"X":-0.17000008,"Y":1},{"Time":210767,"X":0,"Y":1},{"Time":210937,"X":2,"Y":0},{"Time":211108,"X":1,"Y":2},{"Time":211278,"X":1,"Y":0},{"Time":211449,"X":0,"Y":2},{"Time":211534,"X":2,"Y":1},{"Time":211619,"X":0,"Y":1},{"Time":211704,"X":2,"Y":2},{"Time":211789,"X":0,"Y":0},{"Time":211960,"X":1,"Y":2},{"Time":212130,"X":1,"Y":-0.17000008},{"Time":212130,"X":1,"Y":0},{"Time":212301,"X":2,"Y":2},{"Time":212471,"X":2,"Y":0},{"Time":212642,"X":1,"Y":2},{"Time":212812,"X":0,"Y":0},{"Time":212897,"X":2,"Y":2},{"Time":212983,"X":0,"Y":0},{"Time":213068,"X":2,"Y":2},{"Time":213153,"X":0,"Y":1},{"Time":213324,"X":2,"Y":1},{"Time":213494,"X":0,"Y":2},{"Time":213494,"X":-0.17000008,"Y":2.17},{"Time":213664,"X":1,"Y":0},{"Time":213835,"X":1,"Y":2},{"Time":214005,"X":0,"Y":0},{"Time":214176,"X":0,"Y":2},{"Time":214261,"X":1,"Y":0},{"Time":214346,"X":2,"Y":2},{"Time":214432,"X":0,"Y":1},{"Time":214517,"X":2,"Y":0},{"Time":214687,"X":1,"Y":2},{"Time":214858,"X":-0.17000008,"Y":-0.17000008},{"Time":214858,"X":0,"Y":0},{"Time":215028,"X":2,"Y":1},{"Time":215199,"X":0,"Y":1},{"Time":215369,"X":2,"Y":2},{"Time":215539,"X":0,"Y":2},{"Time":215625,"X":2,"Y":1},{"Time":215710,"X":0,"Y":1},{"Time":215795,"X":2,"Y":0},{"Time":215880,"X":0,"Y":0},{"Time":216051,"X":2,"Y":2},{"Time":216221,"X":1,"Y":-0.17000008},{"Time":216221,"X":1,"Y":0},{"Time":216392,"X":0,"Y":2},{"Time":216562,"X":2,"Y":1},{"Time":216733,"X":0,"Y":0},{"Time":216903,"X":1,"Y":2},{"Time":216946,"X":1,"Y":1},{"Time":216988,"X":1,"Y":0},{"Time":217073,"X":2,"Y":2},{"Time":217115,"X":2,"Y":1},{"Time":217158,"X":2,"Y":0},{"Time":217585,"X":0,"Y":0},{"Time":217628,"X":0,"Y":1},{"Time":217670,"X":0,"Y":2},{"Time":217766,"X":2,"Y":0},{"Time":217809,"X":2,"Y":1},{"Time":217851,"X":2,"Y":2},{"Time":218308,"X":2,"Y":0},{"Time":218350,"X":1,"Y":0},{"Time":218393,"X":0,"Y":0},{"Time":218499,"X":2,"Y":2},{"Time":218542,"X":1,"Y":2},{"Time":218584,"X":0,"Y":2},{"Time":219072,"X":2,"Y":0},{"Time":219129,"X":2,"Y":1},{"Time":219186,"X":2,"Y":2},{"Time":219282,"X":0,"Y":0},{"Time":219339,"X":0,"Y":1},{"Time":219396,"X":0,"Y":2},{"Time":219911,"X":2,"Y":0},{"Time":219954,"X":2,"Y":1},{"Time":219996,"X":2,"Y":2},{"Time":220029,"X":1,"Y":2},{"Time":220088,"X":0,"Y":2},{"Time":220147,"X":0,"Y":0},{"Time":220189,"X":1,"Y":0},{"Time":220232,"X":2,"Y":0},{"Time":220856,"X":2,"Y":2},{"Time":220898,"X":2,"Y":1},{"Time":220941,"X":2,"Y":0},{"Time":220983,"X":1,"Y":0},{"Time":221026,"X":0,"Y":0},{"Time":221134,"X":0,"Y":2},{"Time":221176,"X":1,"Y":2},{"Time":221219,"X":2,"Y":2},{"Time":221967,"X":2,"Y":0},{"Time":222024,"X":2,"Y":1},{"Time":222081,"X":2,"Y":2},{"Time":222137,"X":1,"Y":2},{"Time":222194,"X":0,"Y":2},{"Time":222290,"X":0,"Y":0},{"Time":222612,"X":2,"Y":2},{"Time":223012,"X":0,"Y":1},{"Time":223412,"X":2,"Y":0},{"Time":223455,"X":1,"Y":0},{"Time":223498,"X":0,"Y":0},{"Time":223540,"X":0,"Y":1},{"Time":223583,"X":0,"Y":2},{"Time":223847,"X":2,"Y":2},{"Time":224282,"X":2,"Y":0},{"Time":224818,"X":0,"Y":0},{"Time":225353,"X":0,"Y":2},{"Time":225395,"X":0.5,"Y":2},{"Time":225438,"X":1,"Y":2},{"Time":225480,"X":1.5,"Y":2},{"Time":225523,"X":2,"Y":2},{"Time":225565,"X":2,"Y":1.5},{"Time":225608,"X":2,"Y":1},{"Time":225651,"X":2,"Y":0.5},{"Time":225694,"X":2,"Y":0},{"Time":225736,"X":1.5,"Y":0},{"Time":225779,"X":1,"Y":0},{"Time":225821,"X":1,"Y":0.5},{"Time":225864,"X":1,"Y":1},{"Time":225906,"X":1,"Y":1.5},{"Time":225949,"X":1,"Y":2},{"Time":225991,"X":0.5,"Y":2},{"Time":226034,"X":0,"Y":2},{"Time":226077,"X":0,"Y":1.5},{"Time":226120,"X":0,"Y":1},{"Time":226162,"X":0,"Y":0.5},{"Time":226205,"X":0,"Y":0},{"Time":226247,"X":0.5,"Y":0},{"Time":226290,"X":1,"Y":0},{"Time":226332,"X":1.5,"Y":0},{"Time":226375,"X":2,"Y":0},{"Time":226418,"X":2,"Y":0.5},{"Time":226461,"X":2,"Y":1},{"Time":226503,"X":1.5,"Y":1},{"Time":226546,"X":1,"Y":1},{"Time":226588,"X":0.5,"Y":1},{"Time":226631,"X":0,"Y":1},{"Time":226673,"X":0,"Y":1.5},{"Time":226716,"X":0,"Y":2},{"Time":226758,"X":0.5,"Y":2},{"Time":226801,"X":1,"Y":2},{"Time":226844,"X":1.5,"Y":2},{"Time":226887,"X":2,"Y":2},{"Time":226929,"X":2,"Y":1.5},{"Time":226972,"X":2,"Y":1},{"Time":227014,"X":2,"Y":0.5},{"Time":227057,"X":2,"Y":0},{"Time":227099,"X":1.5,"Y":0},{"Time":227142,"X":1,"Y":0},{"Time":227185,"X":0.5,"Y":0},{"Time":227228,"X":0,"Y":0},{"Time":227270,"X":0,"Y":0.5},{"Time":227313,"X":0,"Y":1},{"Time":227355,"X":0,"Y":1.5},{"Time":227398,"X":0,"Y":2},{"Time":227440,"X":0.5,"Y":2},{"Time":227483,"X":1,"Y":2},{"Time":227525,"X":1.5,"Y":2},{"Time":227568,"X":2,"Y":2},{"Time":227611,"X":2,"Y":1.5},{"Time":227654,"X":2,"Y":1},{"Time":227696,"X":2,"Y":0.5},{"Time":227739,"X":2,"Y":0},{"Time":227781,"X":1.5,"Y":0},{"Time":227824,"X":1,"Y":0},{"Time":227866,"X":1,"Y":0.5},{"Time":227909,"X":1,"Y":1},{"Time":227952,"X":1,"Y":1.5},{"Time":227995,"X":1,"Y":2},{"Time":228037,"X":0.5,"Y":2},{"Time":228080,"X":0,"Y":2},{"Time":228122,"X":0,"Y":1.5},{"Time":228165,"X":0,"Y":1},{"Time":228207,"X":0,"Y":0.5},{"Time":228250,"X":0,"Y":0},{"Time":228293,"X":0.5,"Y":0},{"Time":228336,"X":1,"Y":0},{"Time":228378,"X":1.5,"Y":0},{"Time":228421,"X":2,"Y":0},{"Time":228463,"X":2,"Y":0.5},{"Time":228506,"X":2,"Y":1},{"Time":228548,"X":1.5,"Y":1},{"Time":228591,"X":1,"Y":1},{"Time":228633,"X":0.5,"Y":1},{"Time":228676,"X":0,"Y":1},{"Time":228719,"X":0,"Y":1.5},{"Time":228762,"X":0,"Y":2},{"Time":228804,"X":0.5,"Y":2},{"Time":228847,"X":1,"Y":2},{"Time":228889,"X":1.5,"Y":2},{"Time":228932,"X":2,"Y":2},{"Time":228974,"X":2,"Y":1.5},{"Time":229017,"X":2,"Y":1},{"Time":229060,"X":2,"Y":0.5},{"Time":229103,"X":2,"Y":0},{"Time":229145,"X":1.5,"Y":0},{"Time":229188,"X":1,"Y":0},{"Time":229230,"X":1,"Y":0.5},{"Time":229273,"X":1,"Y":1},{"Time":229315,"X":1,"Y":1.5},{"Time":229358,"X":1,"Y":2},{"Time":229401,"X":0.5,"Y":2},{"Time":229444,"X":0,"Y":2},{"Time":229486,"X":0,"Y":1.5},{"Time":229529,"X":0,"Y":1},{"Time":229571,"X":0,"Y":0.5},{"Time":229614,"X":0,"Y":0},{"Time":229656,"X":0.5,"Y":0},{"Time":229699,"X":1,"Y":0},{"Time":229741,"X":1.5,"Y":0},{"Time":229784,"X":2,"Y":0},{"Time":229827,"X":2,"Y":0.5},{"Time":229870,"X":2,"Y":1},{"Time":229912,"X":1.5,"Y":1},{"Time":229955,"X":1,"Y":1},{"Time":229997,"X":0.5,"Y":1},{"Time":230040,"X":0,"Y":1},{"Time":230082,"X":0,"Y":1.5},{"Time":230125,"X":0,"Y":2},{"Time":230168,"X":0.5,"Y":2},{"Time":230211,"X":1,"Y":2}],"AudioFileName":"/cache/audio/9be0fddcd8afc7c5b34a9a6e9289741884123dfac718192b306e7ed012c59a19","ImagePath":"/cache/covers/308a95026148907d4339bbfd11c11783a1e3bf15c87588e584179b4cc029d844"}